{
  "fecha": "2026-07-07",
  "piso_nominal_crudo": 10000,
  "total_operaciones": 476,
  "tickers": {
    "AERBD": [
      {
        "fecha_hora": "2026-07-07T12:27:45.451-03:00",
        "plazo": "24hs",
        "moneda": "USD",
        "precio": 101.8,
        "nominales": 10000,
        "lado": "VENTA"
      }
    ],
    "ARC1D": [
      {
        "fecha_hora": "2026-07-07T15:27:38.019-03:00",
        "plazo": "24hs",
        "moneda": "USD",
        "precio": 108.5,
        "nominales": 30000,
        "lado": "VENTA"
      },
      {
        "fecha_hora": "2026-07-07T15:27:38.02-03:00",
        "plazo": "24hs",
        "moneda": "USD",
        "precio": 108.5,
        "nominales": 28000,
        "lado": "VENTA"
      }
    ],
    "BACHO": [
      {
        "fecha_hora": "2026-07-07T12:06:53.538-03:00",
        "plazo": "24hs",
        "moneda": "ARS",
        "precio": 168130.0,
        "nominales": 30000,
        "lado": "COMPRA"
      }
    ],
    "BYCVD": [
      {
        "fecha_hora": "2026-07-07T16:00:45.108-03:00",
        "plazo": "24hs",
        "moneda": "USD",
        "precio": 103.4,
        "nominales": 25000,
        "lado": "VENTA"
      },
      {
        "fecha_hora": "2026-07-07T12:08:51.216-03:00",
        "plazo": "24hs",
        "moneda": "USD",
        "precio": 103.2,
        "nominales": 15000,
        "lado": "DESCONOCIDO"
      },
      {
        "fecha_hora": "2026-07-07T12:09:39.035-03:00",
        "plazo": "24hs",
        "moneda": "USD",
        "precio": 103.2,
        "nominales": 15000,
        "lado": "DESCONOCIDO"
      },
      {
        "fecha_hora": "2026-07-07T15:57:32.041-03:00",
        "plazo": "24hs",
        "moneda": "USD",
        "precio": 103.2,
        "nominales": 14000,
        "lado": "COMPRA"
      },
      {
        "fecha_hora": "2026-07-07T15:34:18.564-03:00",
        "plazo": "24hs",
        "moneda": "USD",
        "precio": 103.2,
        "nominales": 10000,
        "lado": "COMPRA"
      },
      {
        "fecha_hora": "2026-07-07T15:36:46.597-03:00",
        "plazo": "24hs",
        "moneda": "USD",
        "precio": 103.2,
        "nominales": 10000,
        "lado": "COMPRA"
      }
    ],
    "CP38D": [
      {
        "fecha_hora": "2026-07-07T16:09:32.266-03:00",
        "plazo": "24hs",
        "moneda": "USD",
        "precio": 106.1,
        "nominales": 81000,
        "lado": "COMPRA"
      },
      {
        "fecha_hora": "2026-07-07T16:30:15.942-03:00",
        "plazo": "24hs",
        "moneda": "USD",
        "precio": 106.1,
        "nominales": 81000,
        "lado": "DESCONOCIDO"
      },
      {
        "fecha_hora": "2026-07-07T11:25:43.186-03:00",
        "plazo": "24hs",
        "moneda": "USD",
        "precio": 106.35,
        "nominales": 30000,
        "lado": "COMPRA"
      },
      {
        "fecha_hora": "2026-07-07T11:59:27.934-03:00",
        "plazo": "24hs",
        "moneda": "USD",
        "precio": 106.45,
        "nominales": 23000,
        "lado": "COMPRA"
      },
      {
        "fecha_hora": "2026-07-07T12:03:40.744-03:00",
        "plazo": "24hs",
        "moneda": "USD",
        "precio": 106.45,
        "nominales": 21000,
        "lado": "COMPRA"
      },
      {
        "fecha_hora": "2026-07-07T15:22:36.271-03:00",
        "plazo": "24hs",
        "moneda": "USD",
        "precio": 106.2,
        "nominales": 20000,
        "lado": "VENTA"
      },
      {
        "fecha_hora": "2026-07-07T11:59:32.74-03:00",
        "plazo": "24hs",
        "moneda": "USD",
        "precio": 106.45,
        "nominales": 19000,
        "lado": "COMPRA"
      },
      {
        "fecha_hora": "2026-07-07T16:09:32.267-03:00",
        "plazo": "24hs",
        "moneda": "USD",
        "precio": 106.1,
        "nominales": 19000,
        "lado": "COMPRA"
      },
      {
        "fecha_hora": "2026-07-07T16:30:15.942-03:00",
        "plazo": "24hs",
        "moneda": "USD",
        "precio": 106.1,
        "nominales": 19000,
        "lado": "DESCONOCIDO"
      },
      {
        "fecha_hora": "2026-07-07T16:18:08.642-03:00",
        "plazo": "24hs",
        "moneda": "USD",
        "precio": 106.1,
        "nominales": 18800,
        "lado": "COMPRA"
      },
      {
        "fecha_hora": "2026-07-07T16:18:08.644-03:00",
        "plazo": "24hs",
        "moneda": "USD",
        "precio": 106.1,
        "nominales": 18600,
        "lado": "COMPRA"
      },
      {
        "fecha_hora": "2026-07-07T15:45:23.546-03:00",
        "plazo": "24hs",
        "moneda": "USD",
        "precio": 106.2,
        "nominales": 18000,
        "lado": "COMPRA"
      },
      {
        "fecha_hora": "2026-07-07T11:25:46.021-03:00",
        "plazo": "24hs",
        "moneda": "USD",
        "precio": 106.35,
        "nominales": 15900,
        "lado": "VENTA"
      },
      {
        "fecha_hora": "2026-07-07T15:56:31.222-03:00",
        "plazo": "24hs",
        "moneda": "USD",
        "precio": 106.1,
        "nominales": 13900,
        "lado": "COMPRA"
      },
      {
        "fecha_hora": "2026-07-07T16:38:21.375-03:00",
        "plazo": "24hs",
        "moneda": "USD",
        "precio": 106.1,
        "nominales": 13900,
        "lado": "COMPRA"
      }
    ],
    "CS48O": [
      {
        "fecha_hora": "2026-07-07T12:10:31.683-03:00",
        "plazo": "24hs",
        "moneda": "ARS",
        "precio": 166500.0,
        "nominales": 24597,
        "lado": "VENTA"
      }
    ],
    "CS50D": [
      {
        "fecha_hora": "2026-07-07T12:45:57.071-03:00",
        "plazo": "24hs",
        "moneda": "USD",
        "precio": 106.8,
        "nominales": 13423,
        "lado": "COMPRA"
      }
    ],
    "CS51D": [
      {
        "fecha_hora": "2026-07-07T12:09:24.126-03:00",
        "plazo": "24hs",
        "moneda": "USD",
        "precio": 103.2,
        "nominales": 15988,
        "lado": "VENTA"
      }
    ],
    "DNC3D": [
      {
        "fecha_hora": "2026-07-07T14:06:13.291-03:00",
        "plazo": "24hs",
        "moneda": "USD",
        "precio": 103.0,
        "nominales": 49514,
        "lado": "VENTA"
      },
      {
        "fecha_hora": "2026-07-07T11:39:50.375-03:00",
        "plazo": "24hs",
        "moneda": "USD",
        "precio": 103.0,
        "nominales": 28000,
        "lado": "VENTA"
      },
      {
        "fecha_hora": "2026-07-07T11:06:26.046-03:00",
        "plazo": "24hs",
        "moneda": "USD",
        "precio": 103.0,
        "nominales": 21805,
        "lado": "VENTA"
      }
    ],
    "DNC3O": [
      {
        "fecha_hora": "2026-07-07T11:39:50.371-03:00",
        "plazo": "24hs",
        "moneda": "ARS",
        "precio": 157200.0,
        "nominales": 28000,
        "lado": "VENTA"
      }
    ],
    "DNC5D": [
      {
        "fecha_hora": "2026-07-07T15:27:40.861-03:00",
        "plazo": "24hs",
        "moneda": "USD",
        "precio": 106.8,
        "nominales": 10000,
        "lado": "COMPRA"
      }
    ],
    "DNC5O": [
      {
        "fecha_hora": "2026-07-07T14:03:39.682-03:00",
        "plazo": "24hs",
        "moneda": "ARS",
        "precio": 163000.0,
        "nominales": 20000,
        "lado": "VENTA"
      },
      {
        "fecha_hora": "2026-07-07T15:25:01.621-03:00",
        "plazo": "24hs",
        "moneda": "ARS",
        "precio": 162540.0,
        "nominales": 10000,
        "lado": "VENTA"
      },
      {
        "fecha_hora": "2026-07-07T15:31:42.139-03:00",
        "plazo": "24hs",
        "moneda": "ARS",
        "precio": 162500.0,
        "nominales": 10000,
        "lado": "VENTA"
      }
    ],
    "DNC7D": [
      {
        "fecha_hora": "2026-07-07T10:58:49.813-03:00",
        "plazo": "CI",
        "moneda": "USD",
        "precio": 108.95,
        "nominales": 16100,
        "lado": "COMPRA"
      }
    ],
    "DNC7O": [
      {
        "fecha_hora": "2026-07-07T12:31:07.682-03:00",
        "plazo": "CI",
        "moneda": "ARS",
        "precio": 164920.0,
        "nominales": 12800,
        "lado": "VENTA"
      }
    ],
    "DNCAD": [
      {
        "fecha_hora": "2026-07-07T11:24:57.745-03:00",
        "plazo": "24hs",
        "moneda": "USD",
        "precio": 105.25,
        "nominales": 30000,
        "lado": "COMPRA"
      },
      {
        "fecha_hora": "2026-07-07T12:01:16.882-03:00",
        "plazo": "24hs",
        "moneda": "USD",
        "precio": 105.3,
        "nominales": 23500,
        "lado": "COMPRA"
      },
      {
        "fecha_hora": "2026-07-07T12:05:51.216-03:00",
        "plazo": "24hs",
        "moneda": "USD",
        "precio": 105.25,
        "nominales": 15000,
        "lado": "COMPRA"
      },
      {
        "fecha_hora": "2026-07-07T12:05:51.17-03:00",
        "plazo": "24hs",
        "moneda": "USD",
        "precio": 105.25,
        "nominales": 15000,
        "lado": "COMPRA"
      },
      {
        "fecha_hora": "2026-07-07T12:18:21.075-03:00",
        "plazo": "24hs",
        "moneda": "USD",
        "precio": 105.3,
        "nominales": 14500,
        "lado": "COMPRA"
      },
      {
        "fecha_hora": "2026-07-07T12:00:25.759-03:00",
        "plazo": "24hs",
        "moneda": "USD",
        "precio": 105.3,
        "nominales": 14400,
        "lado": "COMPRA"
      },
      {
        "fecha_hora": "2026-07-07T12:00:25.759-03:00",
        "plazo": "24hs",
        "moneda": "USD",
        "precio": 105.3,
        "nominales": 10000,
        "lado": "COMPRA"
      }
    ],
    "DNCAO": [
      {
        "fecha_hora": "2026-07-07T12:11:23.613-03:00",
        "plazo": "24hs",
        "moneda": "ARS",
        "precio": 160950.0,
        "nominales": 61000,
        "lado": "COMPRA"
      },
      {
        "fecha_hora": "2026-07-07T14:09:43.788-03:00",
        "plazo": "24hs",
        "moneda": "ARS",
        "precio": 161400.0,
        "nominales": 30000,
        "lado": "COMPRA"
      },
      {
        "fecha_hora": "2026-07-07T16:12:49.573-03:00",
        "plazo": "24hs",
        "moneda": "ARS",
        "precio": 161600.0,
        "nominales": 20900,
        "lado": "COMPRA"
      },
      {
        "fecha_hora": "2026-07-07T12:05:51.321-03:00",
        "plazo": "24hs",
        "moneda": "ARS",
        "precio": 160900.0,
        "nominales": 15000,
        "lado": "VENTA"
      },
      {
        "fecha_hora": "2026-07-07T12:05:51.377-03:00",
        "plazo": "24hs",
        "moneda": "ARS",
        "precio": 160900.0,
        "nominales": 15000,
        "lado": "VENTA"
      },
      {
        "fecha_hora": "2026-07-07T15:34:17.759-03:00",
        "plazo": "24hs",
        "moneda": "ARS",
        "precio": 161390.0,
        "nominales": 11800,
        "lado": "COMPRA"
      },
      {
        "fecha_hora": "2026-07-07T14:01:11.681-03:00",
        "plazo": "24hs",
        "moneda": "ARS",
        "precio": 161540.0,
        "nominales": 10800,
        "lado": "COMPRA"
      }
    ],
    "EAC4D": [
      {
        "fecha_hora": "2026-07-07T14:01:17.762-03:00",
        "plazo": "24hs",
        "moneda": "USD",
        "precio": 102.9,
        "nominales": 12000,
        "lado": "VENTA"
      },
      {
        "fecha_hora": "2026-07-07T13:53:49.828-03:00",
        "plazo": "24hs",
        "moneda": "USD",
        "precio": 103.1,
        "nominales": 10000,
        "lado": "COMPRA"
      }
    ],
    "HJCID": [
      {
        "fecha_hora": "2026-07-07T15:37:48.294-03:00",
        "plazo": "24hs",
        "moneda": "USD",
        "precio": 102.75,
        "nominales": 10000,
        "lado": "COMPRA"
      }
    ],
    "IRCPD": [
      {
        "fecha_hora": "2026-07-07T12:36:53.307-03:00",
        "plazo": "24hs",
        "moneda": "USD",
        "precio": 109.9,
        "nominales": 12188,
        "lado": "COMPRA"
      }
    ],
    "IRCPO": [
      {
        "fecha_hora": "2026-07-07T12:36:53.287-03:00",
        "plazo": "24hs",
        "moneda": "ARS",
        "precio": 168000.0,
        "nominales": 12188,
        "lado": "VENTA"
      }
    ],
    "LMS7O": [
      {
        "fecha_hora": "2026-07-07T15:58:02.862-03:00",
        "plazo": "24hs",
        "moneda": "ARS",
        "precio": 133500.0,
        "nominales": 45317,
        "lado": "COMPRA"
      },
      {
        "fecha_hora": "2026-07-07T15:51:28.02-03:00",
        "plazo": "24hs",
        "moneda": "ARS",
        "precio": 133500.0,
        "nominales": 12679,
        "lado": "VENTA"
      }
    ],
    "LOC5D": [
      {
        "fecha_hora": "2026-07-07T15:55:46.155-03:00",
        "plazo": "24hs",
        "moneda": "USD",
        "precio": 107.1,
        "nominales": 10000,
        "lado": "VENTA"
      }
    ],
    "LUC5D": [
      {
        "fecha_hora": "2026-07-07T15:47:20.52-03:00",
        "plazo": "24hs",
        "moneda": "USD",
        "precio": 103.0,
        "nominales": 29299,
        "lado": "COMPRA"
      }
    ],
    "MCC1O": [
      {
        "fecha_hora": "2026-07-07T12:31:04.415-03:00",
        "plazo": "24hs",
        "moneda": "ARS",
        "precio": 160000.0,
        "nominales": 10000,
        "lado": "COMPRA"
      }
    ],
    "MCC2D": [
      {
        "fecha_hora": "2026-07-07T16:40:39.749-03:00",
        "plazo": "24hs",
        "moneda": "USD",
        "precio": 102.1,
        "nominales": 50000,
        "lado": "COMPRA"
      }
    ],
    "MCC3D": [
      {
        "fecha_hora": "2026-07-07T16:19:02.108-03:00",
        "plazo": "24hs",
        "moneda": "USD",
        "precio": 102.5,
        "nominales": 11772,
        "lado": "COMPRA"
      }
    ],
    "MGCMD": [
      {
        "fecha_hora": "2026-07-07T16:12:19.88-03:00",
        "plazo": "24hs",
        "moneda": "USD",
        "precio": 111.2,
        "nominales": 10000,
        "lado": "VENTA"
      }
    ],
    "MGCMO": [
      {
        "fecha_hora": "2026-07-07T16:11:50.387-03:00",
        "plazo": "24hs",
        "moneda": "ARS",
        "precio": 168970.0,
        "nominales": 10000,
        "lado": "VENTA"
      }
    ],
    "MGCOD": [
      {
        "fecha_hora": "2026-07-07T14:40:25.581-03:00",
        "plazo": "24hs",
        "moneda": "USD",
        "precio": 107.85,
        "nominales": 20000,
        "lado": "COMPRA"
      },
      {
        "fecha_hora": "2026-07-07T15:12:28.348-03:00",
        "plazo": "24hs",
        "moneda": "USD",
        "precio": 107.85,
        "nominales": 20000,
        "lado": "COMPRA"
      },
      {
        "fecha_hora": "2026-07-07T12:09:48.536-03:00",
        "plazo": "24hs",
        "moneda": "USD",
        "precio": 107.75,
        "nominales": 10000,
        "lado": "VENTA"
      }
    ],
    "MGCOO": [
      {
        "fecha_hora": "2026-07-07T12:43:57.745-03:00",
        "plazo": "24hs",
        "moneda": "ARS",
        "precio": 165000.0,
        "nominales": 20000,
        "lado": "COMPRA"
      },
      {
        "fecha_hora": "2026-07-07T14:41:28.635-03:00",
        "plazo": "24hs",
        "moneda": "ARS",
        "precio": 164700.0,
        "nominales": 15000,
        "lado": "VENTA"
      },
      {
        "fecha_hora": "2026-07-07T13:33:30.404-03:00",
        "plazo": "24hs",
        "moneda": "ARS",
        "precio": 165000.0,
        "nominales": 10000,
        "lado": "VENTA"
      },
      {
        "fecha_hora": "2026-07-07T16:32:58.665-03:00",
        "plazo": "24hs",
        "moneda": "ARS",
        "precio": 165640.0,
        "nominales": 10000,
        "lado": "DESCONOCIDO"
      }
    ],
    "MGCQD": [
      {
        "fecha_hora": "2026-07-07T15:43:05.494-03:00",
        "plazo": "24hs",
        "moneda": "USD",
        "precio": 108.35,
        "nominales": 12089,
        "lado": "COMPRA"
      }
    ],
    "MGCQO": [
      {
        "fecha_hora": "2026-07-07T11:59:07.53-03:00",
        "plazo": "24hs",
        "moneda": "ARS",
        "precio": 165250.0,
        "nominales": 10000,
        "lado": "VENTA"
      }
    ],
    "MGCRD": [
      {
        "fecha_hora": "2026-07-07T11:54:14.23-03:00",
        "plazo": "24hs",
        "moneda": "USD",
        "precio": 106.2,
        "nominales": 20000,
        "lado": "VENTA"
      },
      {
        "fecha_hora": "2026-07-07T10:43:11.042-03:00",
        "plazo": "24hs",
        "moneda": "USD",
        "precio": 106.3,
        "nominales": 16000,
        "lado": "VENTA"
      },
      {
        "fecha_hora": "2026-07-07T14:02:13.722-03:00",
        "plazo": "CI",
        "moneda": "USD",
        "precio": 106.4,
        "nominales": 16000,
        "lado": "COMPRA"
      },
      {
        "fecha_hora": "2026-07-07T15:53:42.928-03:00",
        "plazo": "24hs",
        "moneda": "USD",
        "precio": 106.25,
        "nominales": 14000,
        "lado": "COMPRA"
      },
      {
        "fecha_hora": "2026-07-07T16:47:54.448-03:00",
        "plazo": "24hs",
        "moneda": "USD",
        "precio": 106.25,
        "nominales": 14000,
        "lado": "VENTA"
      },
      {
        "fecha_hora": "2026-07-07T10:57:12.749-03:00",
        "plazo": "24hs",
        "moneda": "USD",
        "precio": 106.4,
        "nominales": 10000,
        "lado": "COMPRA"
      },
      {
        "fecha_hora": "2026-07-07T10:58:11.046-03:00",
        "plazo": "24hs",
        "moneda": "USD",
        "precio": 106.4,
        "nominales": 10000,
        "lado": "COMPRA"
      },
      {
        "fecha_hora": "2026-07-07T10:58:11.307-03:00",
        "plazo": "24hs",
        "moneda": "USD",
        "precio": 106.4,
        "nominales": 10000,
        "lado": "COMPRA"
      },
      {
        "fecha_hora": "2026-07-07T11:16:01.951-03:00",
        "plazo": "24hs",
        "moneda": "USD",
        "precio": 106.4,
        "nominales": 10000,
        "lado": "COMPRA"
      },
      {
        "fecha_hora": "2026-07-07T11:19:13.86-03:00",
        "plazo": "24hs",
        "moneda": "USD",
        "precio": 106.4,
        "nominales": 10000,
        "lado": "COMPRA"
      },
      {
        "fecha_hora": "2026-07-07T11:44:21.726-03:00",
        "plazo": "24hs",
        "moneda": "USD",
        "precio": 106.5,
        "nominales": 10000,
        "lado": "COMPRA"
      },
      {
        "fecha_hora": "2026-07-07T11:47:19.854-03:00",
        "plazo": "24hs",
        "moneda": "USD",
        "precio": 106.25,
        "nominales": 10000,
        "lado": "VENTA"
      },
      {
        "fecha_hora": "2026-07-07T11:48:31.036-03:00",
        "plazo": "24hs",
        "moneda": "USD",
        "precio": 106.25,
        "nominales": 10000,
        "lado": "VENTA"
      },
      {
        "fecha_hora": "2026-07-07T11:53:27.763-03:00",
        "plazo": "24hs",
        "moneda": "USD",
        "precio": 106.3,
        "nominales": 10000,
        "lado": "COMPRA"
      },
      {
        "fecha_hora": "2026-07-07T12:04:15.901-03:00",
        "plazo": "24hs",
        "moneda": "USD",
        "precio": 106.3,
        "nominales": 10000,
        "lado": "COMPRA"
      },
      {
        "fecha_hora": "2026-07-07T12:29:22.627-03:00",
        "plazo": "24hs",
        "moneda": "USD",
        "precio": 106.3,
        "nominales": 10000,
        "lado": "VENTA"
      },
      {
        "fecha_hora": "2026-07-07T12:29:24.508-03:00",
        "plazo": "24hs",
        "moneda": "USD",
        "precio": 106.3,
        "nominales": 10000,
        "lado": "VENTA"
      },
      {
        "fecha_hora": "2026-07-07T12:29:25.302-03:00",
        "plazo": "24hs",
        "moneda": "USD",
        "precio": 106.3,
        "nominales": 10000,
        "lado": "VENTA"
      },
      {
        "fecha_hora": "2026-07-07T12:29:26.23-03:00",
        "plazo": "24hs",
        "moneda": "USD",
        "precio": 106.3,
        "nominales": 10000,
        "lado": "VENTA"
      },
      {
        "fecha_hora": "2026-07-07T12:32:18.847-03:00",
        "plazo": "24hs",
        "moneda": "USD",
        "precio": 106.3,
        "nominales": 10000,
        "lado": "VENTA"
      },
      {
        "fecha_hora": "2026-07-07T12:32:19.807-03:00",
        "plazo": "24hs",
        "moneda": "USD",
        "precio": 106.3,
        "nominales": 10000,
        "lado": "VENTA"
      },
      {
        "fecha_hora": "2026-07-07T12:32:20.361-03:00",
        "plazo": "24hs",
        "moneda": "USD",
        "precio": 106.3,
        "nominales": 10000,
        "lado": "VENTA"
      },
      {
        "fecha_hora": "2026-07-07T12:32:20.824-03:00",
        "plazo": "24hs",
        "moneda": "USD",
        "precio": 106.3,
        "nominales": 10000,
        "lado": "VENTA"
      },
      {
        "fecha_hora": "2026-07-07T12:33:22.155-03:00",
        "plazo": "24hs",
        "moneda": "USD",
        "precio": 106.25,
        "nominales": 10000,
        "lado": "VENTA"
      },
      {
        "fecha_hora": "2026-07-07T12:33:38.724-03:00",
        "plazo": "24hs",
        "moneda": "USD",
        "precio": 106.35,
        "nominales": 10000,
        "lado": "COMPRA"
      },
      {
        "fecha_hora": "2026-07-07T12:34:02.701-03:00",
        "plazo": "24hs",
        "moneda": "USD",
        "precio": 106.25,
        "nominales": 10000,
        "lado": "VENTA"
      },
      {
        "fecha_hora": "2026-07-07T12:34:19.119-03:00",
        "plazo": "24hs",
        "moneda": "USD",
        "precio": 106.25,
        "nominales": 10000,
        "lado": "VENTA"
      },
      {
        "fecha_hora": "2026-07-07T12:34:29.412-03:00",
        "plazo": "24hs",
        "moneda": "USD",
        "precio": 106.25,
        "nominales": 10000,
        "lado": "VENTA"
      },
      {
        "fecha_hora": "2026-07-07T12:35:55.921-03:00",
        "plazo": "24hs",
        "moneda": "USD",
        "precio": 106.3,
        "nominales": 10000,
        "lado": "COMPRA"
      },
      {
        "fecha_hora": "2026-07-07T12:36:27.328-03:00",
        "plazo": "CI",
        "moneda": "USD",
        "precio": 106.4,
        "nominales": 10000,
        "lado": "COMPRA"
      },
      {
        "fecha_hora": "2026-07-07T12:36:48.33-03:00",
        "plazo": "24hs",
        "moneda": "USD",
        "precio": 106.25,
        "nominales": 10000,
        "lado": "VENTA"
      },
      {
        "fecha_hora": "2026-07-07T12:38:14.354-03:00",
        "plazo": "24hs",
        "moneda": "USD",
        "precio": 106.25,
        "nominales": 10000,
        "lado": "VENTA"
      },
      {
        "fecha_hora": "2026-07-07T12:40:27.939-03:00",
        "plazo": "24hs",
        "moneda": "USD",
        "precio": 106.25,
        "nominales": 10000,
        "lado": "VENTA"
      },
      {
        "fecha_hora": "2026-07-07T12:41:57.908-03:00",
        "plazo": "24hs",
        "moneda": "USD",
        "precio": 106.25,
        "nominales": 10000,
        "lado": "VENTA"
      },
      {
        "fecha_hora": "2026-07-07T12:41:58.058-03:00",
        "plazo": "24hs",
        "moneda": "USD",
        "precio": 106.25,
        "nominales": 10000,
        "lado": "VENTA"
      },
      {
        "fecha_hora": "2026-07-07T12:41:57.998-03:00",
        "plazo": "24hs",
        "moneda": "USD",
        "precio": 106.25,
        "nominales": 10000,
        "lado": "VENTA"
      },
      {
        "fecha_hora": "2026-07-07T12:41:57.947-03:00",
        "plazo": "24hs",
        "moneda": "USD",
        "precio": 106.25,
        "nominales": 10000,
        "lado": "VENTA"
      },
      {
        "fecha_hora": "2026-07-07T12:45:34.798-03:00",
        "plazo": "24hs",
        "moneda": "USD",
        "precio": 106.25,
        "nominales": 10000,
        "lado": "VENTA"
      },
      {
        "fecha_hora": "2026-07-07T12:51:49.895-03:00",
        "plazo": "24hs",
        "moneda": "USD",
        "precio": 106.25,
        "nominales": 10000,
        "lado": "VENTA"
      },
      {
        "fecha_hora": "2026-07-07T12:52:23.741-03:00",
        "plazo": "24hs",
        "moneda": "USD",
        "precio": 106.25,
        "nominales": 10000,
        "lado": "VENTA"
      },
      {
        "fecha_hora": "2026-07-07T13:11:21.554-03:00",
        "plazo": "CI",
        "moneda": "USD",
        "precio": 106.4,
        "nominales": 10000,
        "lado": "COMPRA"
      },
      {
        "fecha_hora": "2026-07-07T13:46:15.907-03:00",
        "plazo": "24hs",
        "moneda": "USD",
        "precio": 106.25,
        "nominales": 10000,
        "lado": "DESCONOCIDO"
      },
      {
        "fecha_hora": "2026-07-07T13:57:32.057-03:00",
        "plazo": "CI",
        "moneda": "USD",
        "precio": 106.1,
        "nominales": 10000,
        "lado": "VENTA"
      },
      {
        "fecha_hora": "2026-07-07T14:02:56.517-03:00",
        "plazo": "CI",
        "moneda": "USD",
        "precio": 106.0,
        "nominales": 10000,
        "lado": "VENTA"
      },
      {
        "fecha_hora": "2026-07-07T14:19:15.562-03:00",
        "plazo": "24hs",
        "moneda": "USD",
        "precio": 106.3,
        "nominales": 10000,
        "lado": "COMPRA"
      },
      {
        "fecha_hora": "2026-07-07T14:32:26.506-03:00",
        "plazo": "24hs",
        "moneda": "USD",
        "precio": 106.3,
        "nominales": 10000,
        "lado": "COMPRA"
      },
      {
        "fecha_hora": "2026-07-07T14:35:14.042-03:00",
        "plazo": "24hs",
        "moneda": "USD",
        "precio": 106.3,
        "nominales": 10000,
        "lado": "COMPRA"
      },
      {
        "fecha_hora": "2026-07-07T15:31:31.757-03:00",
        "plazo": "CI",
        "moneda": "USD",
        "precio": 106.3,
        "nominales": 10000,
        "lado": "COMPRA"
      },
      {
        "fecha_hora": "2026-07-07T16:49:17.564-03:00",
        "plazo": "24hs",
        "moneda": "USD",
        "precio": 106.4,
        "nominales": 10000,
        "lado": "COMPRA"
      }
    ],
    "MGCRO": [
      {
        "fecha_hora": "2026-07-07T16:03:28.589-03:00",
        "plazo": "24hs",
        "moneda": "ARS",
        "precio": 162150.0,
        "nominales": 30000,
        "lado": "COMPRA"
      },
      {
        "fecha_hora": "2026-07-07T12:33:50.951-03:00",
        "plazo": "24hs",
        "moneda": "ARS",
        "precio": 162300.0,
        "nominales": 19000,
        "lado": "COMPRA"
      },
      {
        "fecha_hora": "2026-07-07T15:22:22.635-03:00",
        "plazo": "24hs",
        "moneda": "ARS",
        "precio": 162150.0,
        "nominales": 15000,
        "lado": "VENTA"
      },
      {
        "fecha_hora": "2026-07-07T16:10:52.571-03:00",
        "plazo": "24hs",
        "moneda": "ARS",
        "precio": 162150.0,
        "nominales": 14000,
        "lado": "COMPRA"
      },
      {
        "fecha_hora": "2026-07-07T15:52:37.021-03:00",
        "plazo": "24hs",
        "moneda": "ARS",
        "precio": 162150.0,
        "nominales": 11000,
        "lado": "COMPRA"
      },
      {
        "fecha_hora": "2026-07-07T10:32:21.292-03:00",
        "plazo": "CI",
        "moneda": "ARS",
        "precio": 165180.0,
        "nominales": 10000,
        "lado": "COMPRA"
      },
      {
        "fecha_hora": "2026-07-07T11:06:28.232-03:00",
        "plazo": "24hs",
        "moneda": "ARS",
        "precio": 162540.0,
        "nominales": 10000,
        "lado": "VENTA"
      },
      {
        "fecha_hora": "2026-07-07T11:40:51.725-03:00",
        "plazo": "24hs",
        "moneda": "ARS",
        "precio": 162770.0,
        "nominales": 10000,
        "lado": "COMPRA"
      },
      {
        "fecha_hora": "2026-07-07T11:48:10.206-03:00",
        "plazo": "24hs",
        "moneda": "ARS",
        "precio": 162300.0,
        "nominales": 10000,
        "lado": "COMPRA"
      },
      {
        "fecha_hora": "2026-07-07T11:59:35.8-03:00",
        "plazo": "24hs",
        "moneda": "ARS",
        "precio": 162300.0,
        "nominales": 10000,
        "lado": "COMPRA"
      },
      {
        "fecha_hora": "2026-07-07T12:24:41.123-03:00",
        "plazo": "24hs",
        "moneda": "ARS",
        "precio": 162300.0,
        "nominales": 10000,
        "lado": "COMPRA"
      },
      {
        "fecha_hora": "2026-07-07T12:29:22.48-03:00",
        "plazo": "24hs",
        "moneda": "ARS",
        "precio": 162300.0,
        "nominales": 10000,
        "lado": "COMPRA"
      },
      {
        "fecha_hora": "2026-07-07T12:29:24.359-03:00",
        "plazo": "24hs",
        "moneda": "ARS",
        "precio": 162300.0,
        "nominales": 10000,
        "lado": "COMPRA"
      },
      {
        "fecha_hora": "2026-07-07T12:29:25.157-03:00",
        "plazo": "24hs",
        "moneda": "ARS",
        "precio": 162300.0,
        "nominales": 10000,
        "lado": "COMPRA"
      },
      {
        "fecha_hora": "2026-07-07T12:29:26.05-03:00",
        "plazo": "24hs",
        "moneda": "ARS",
        "precio": 162300.0,
        "nominales": 10000,
        "lado": "COMPRA"
      },
      {
        "fecha_hora": "2026-07-07T12:29:26.891-03:00",
        "plazo": "24hs",
        "moneda": "ARS",
        "precio": 162300.0,
        "nominales": 10000,
        "lado": "COMPRA"
      },
      {
        "fecha_hora": "2026-07-07T12:32:18.237-03:00",
        "plazo": "24hs",
        "moneda": "ARS",
        "precio": 162300.0,
        "nominales": 10000,
        "lado": "COMPRA"
      },
      {
        "fecha_hora": "2026-07-07T12:32:18.615-03:00",
        "plazo": "24hs",
        "moneda": "ARS",
        "precio": 162300.0,
        "nominales": 10000,
        "lado": "COMPRA"
      },
      {
        "fecha_hora": "2026-07-07T12:32:18.71-03:00",
        "plazo": "24hs",
        "moneda": "ARS",
        "precio": 162300.0,
        "nominales": 10000,
        "lado": "COMPRA"
      },
      {
        "fecha_hora": "2026-07-07T12:32:19.664-03:00",
        "plazo": "24hs",
        "moneda": "ARS",
        "precio": 162300.0,
        "nominales": 10000,
        "lado": "COMPRA"
      },
      {
        "fecha_hora": "2026-07-07T12:32:20.65-03:00",
        "plazo": "24hs",
        "moneda": "ARS",
        "precio": 162300.0,
        "nominales": 10000,
        "lado": "COMPRA"
      },
      {
        "fecha_hora": "2026-07-07T12:33:20.658-03:00",
        "plazo": "24hs",
        "moneda": "ARS",
        "precio": 162300.0,
        "nominales": 10000,
        "lado": "COMPRA"
      },
      {
        "fecha_hora": "2026-07-07T12:33:53.76-03:00",
        "plazo": "24hs",
        "moneda": "ARS",
        "precio": 162300.0,
        "nominales": 10000,
        "lado": "COMPRA"
      },
      {
        "fecha_hora": "2026-07-07T12:33:57.929-03:00",
        "plazo": "24hs",
        "moneda": "ARS",
        "precio": 162300.0,
        "nominales": 10000,
        "lado": "COMPRA"
      },
      {
        "fecha_hora": "2026-07-07T12:34:17.727-03:00",
        "plazo": "24hs",
        "moneda": "ARS",
        "precio": 162300.0,
        "nominales": 10000,
        "lado": "COMPRA"
      },
      {
        "fecha_hora": "2026-07-07T12:34:24.994-03:00",
        "plazo": "24hs",
        "moneda": "ARS",
        "precio": 162300.0,
        "nominales": 10000,
        "lado": "COMPRA"
      },
      {
        "fecha_hora": "2026-07-07T12:34:31.257-03:00",
        "plazo": "24hs",
        "moneda": "ARS",
        "precio": 162300.0,
        "nominales": 10000,
        "lado": "COMPRA"
      },
      {
        "fecha_hora": "2026-07-07T12:36:17.89-03:00",
        "plazo": "24hs",
        "moneda": "ARS",
        "precio": 162300.0,
        "nominales": 10000,
        "lado": "COMPRA"
      },
      {
        "fecha_hora": "2026-07-07T12:36:45.23-03:00",
        "plazo": "24hs",
        "moneda": "ARS",
        "precio": 162300.0,
        "nominales": 10000,
        "lado": "COMPRA"
      },
      {
        "fecha_hora": "2026-07-07T12:37:01.745-03:00",
        "plazo": "24hs",
        "moneda": "ARS",
        "precio": 162300.0,
        "nominales": 10000,
        "lado": "COMPRA"
      },
      {
        "fecha_hora": "2026-07-07T12:38:08.961-03:00",
        "plazo": "24hs",
        "moneda": "ARS",
        "precio": 162300.0,
        "nominales": 10000,
        "lado": "COMPRA"
      },
      {
        "fecha_hora": "2026-07-07T12:39:11.733-03:00",
        "plazo": "24hs",
        "moneda": "ARS",
        "precio": 162300.0,
        "nominales": 10000,
        "lado": "COMPRA"
      },
      {
        "fecha_hora": "2026-07-07T12:40:26.397-03:00",
        "plazo": "24hs",
        "moneda": "ARS",
        "precio": 162300.0,
        "nominales": 10000,
        "lado": "COMPRA"
      },
      {
        "fecha_hora": "2026-07-07T12:43:30.83-03:00",
        "plazo": "24hs",
        "moneda": "ARS",
        "precio": 162300.0,
        "nominales": 10000,
        "lado": "COMPRA"
      },
      {
        "fecha_hora": "2026-07-07T12:45:26.074-03:00",
        "plazo": "24hs",
        "moneda": "ARS",
        "precio": 162300.0,
        "nominales": 10000,
        "lado": "COMPRA"
      },
      {
        "fecha_hora": "2026-07-07T12:45:33.21-03:00",
        "plazo": "24hs",
        "moneda": "ARS",
        "precio": 162300.0,
        "nominales": 10000,
        "lado": "COMPRA"
      },
      {
        "fecha_hora": "2026-07-07T12:51:47.939-03:00",
        "plazo": "24hs",
        "moneda": "ARS",
        "precio": 162300.0,
        "nominales": 10000,
        "lado": "COMPRA"
      },
      {
        "fecha_hora": "2026-07-07T12:52:19.54-03:00",
        "plazo": "24hs",
        "moneda": "ARS",
        "precio": 162230.0,
        "nominales": 10000,
        "lado": "VENTA"
      },
      {
        "fecha_hora": "2026-07-07T12:52:19.541-03:00",
        "plazo": "24hs",
        "moneda": "ARS",
        "precio": 162220.0,
        "nominales": 10000,
        "lado": "VENTA"
      },
      {
        "fecha_hora": "2026-07-07T12:52:23.591-03:00",
        "plazo": "24hs",
        "moneda": "ARS",
        "precio": 162200.0,
        "nominales": 10000,
        "lado": "COMPRA"
      },
      {
        "fecha_hora": "2026-07-07T12:52:35.148-03:00",
        "plazo": "24hs",
        "moneda": "ARS",
        "precio": 162200.0,
        "nominales": 10000,
        "lado": "COMPRA"
      },
      {
        "fecha_hora": "2026-07-07T12:52:48.602-03:00",
        "plazo": "24hs",
        "moneda": "ARS",
        "precio": 162200.0,
        "nominales": 10000,
        "lado": "COMPRA"
      },
      {
        "fecha_hora": "2026-07-07T13:02:08.693-03:00",
        "plazo": "24hs",
        "moneda": "ARS",
        "precio": 162200.0,
        "nominales": 10000,
        "lado": "COMPRA"
      },
      {
        "fecha_hora": "2026-07-07T13:14:31-03:00",
        "plazo": "24hs",
        "moneda": "ARS",
        "precio": 162200.0,
        "nominales": 10000,
        "lado": "COMPRA"
      },
      {
        "fecha_hora": "2026-07-07T13:57:18.724-03:00",
        "plazo": "CI",
        "moneda": "ARS",
        "precio": 161700.0,
        "nominales": 10000,
        "lado": "VENTA"
      },
      {
        "fecha_hora": "2026-07-07T13:57:32.029-03:00",
        "plazo": "CI",
        "moneda": "ARS",
        "precio": 161700.0,
        "nominales": 10000,
        "lado": "VENTA"
      },
      {
        "fecha_hora": "2026-07-07T14:07:49.978-03:00",
        "plazo": "24hs",
        "moneda": "ARS",
        "precio": 162150.0,
        "nominales": 10000,
        "lado": "VENTA"
      },
      {
        "fecha_hora": "2026-07-07T15:22:22.635-03:00",
        "plazo": "24hs",
        "moneda": "ARS",
        "precio": 162160.0,
        "nominales": 10000,
        "lado": "VENTA"
      },
      {
        "fecha_hora": "2026-07-07T15:38:07.555-03:00",
        "plazo": "24hs",
        "moneda": "ARS",
        "precio": 162070.0,
        "nominales": 10000,
        "lado": "VENTA"
      },
      {
        "fecha_hora": "2026-07-07T15:47:03.258-03:00",
        "plazo": "24hs",
        "moneda": "ARS",
        "precio": 162070.0,
        "nominales": 10000,
        "lado": "DESCONOCIDO"
      },
      {
        "fecha_hora": "2026-07-07T16:08:37.787-03:00",
        "plazo": "24hs",
        "moneda": "ARS",
        "precio": 162150.0,
        "nominales": 10000,
        "lado": "COMPRA"
      },
      {
        "fecha_hora": "2026-07-07T16:10:21.447-03:00",
        "plazo": "24hs",
        "moneda": "ARS",
        "precio": 162150.0,
        "nominales": 10000,
        "lado": "COMPRA"
      },
      {
        "fecha_hora": "2026-07-07T16:46:11.642-03:00",
        "plazo": "24hs",
        "moneda": "ARS",
        "precio": 163300.0,
        "nominales": 10000,
        "lado": "COMPRA"
      },
      {
        "fecha_hora": "2026-07-07T16:48:22.852-03:00",
        "plazo": "24hs",
        "moneda": "ARS",
        "precio": 163300.0,
        "nominales": 10000,
        "lado": "COMPRA"
      }
    ],
    "MGCTD": [
      {
        "fecha_hora": "2026-07-07T11:10:50.977-03:00",
        "plazo": "CI",
        "moneda": "USD",
        "precio": 102.0,
        "nominales": 20000,
        "lado": "VENTA"
      }
    ],
    "MIC4D": [
      {
        "fecha_hora": "2026-07-07T16:19:31.217-03:00",
        "plazo": "24hs",
        "moneda": "USD",
        "precio": 102.7,
        "nominales": 10000,
        "lado": "VENTA"
      }
    ],
    "MR46D": [
      {
        "fecha_hora": "2026-07-07T16:05:42.419-03:00",
        "plazo": "24hs",
        "moneda": "USD",
        "precio": 85.0,
        "nominales": 75809,
        "lado": "COMPRA"
      },
      {
        "fecha_hora": "2026-07-07T12:13:43.884-03:00",
        "plazo": "24hs",
        "moneda": "USD",
        "precio": 84.57,
        "nominales": 25979,
        "lado": "VENTA"
      },
      {
        "fecha_hora": "2026-07-07T11:56:49.547-03:00",
        "plazo": "24hs",
        "moneda": "USD",
        "precio": 84.54,
        "nominales": 23939,
        "lado": "VENTA"
      },
      {
        "fecha_hora": "2026-07-07T16:51:23.09-03:00",
        "plazo": "24hs",
        "moneda": "USD",
        "precio": 85.1,
        "nominales": 19183,
        "lado": "VENTA"
      },
      {
        "fecha_hora": "2026-07-07T11:17:58.331-03:00",
        "plazo": "24hs",
        "moneda": "USD",
        "precio": 84.5,
        "nominales": 16995,
        "lado": "COMPRA"
      },
      {
        "fecha_hora": "2026-07-07T11:04:31.492-03:00",
        "plazo": "24hs",
        "moneda": "USD",
        "precio": 84.22,
        "nominales": 16546,
        "lado": "VENTA"
      },
      {
        "fecha_hora": "2026-07-07T11:56:38.362-03:00",
        "plazo": "24hs",
        "moneda": "USD",
        "precio": 84.54,
        "nominales": 12729,
        "lado": "VENTA"
      },
      {
        "fecha_hora": "2026-07-07T12:09:37.163-03:00",
        "plazo": "24hs",
        "moneda": "USD",
        "precio": 84.56,
        "nominales": 11504,
        "lado": "VENTA"
      },
      {
        "fecha_hora": "2026-07-07T12:29:26.077-03:00",
        "plazo": "24hs",
        "moneda": "USD",
        "precio": 84.97,
        "nominales": 10047,
        "lado": "COMPRA"
      }
    ],
    "MR46O": [
      {
        "fecha_hora": "2026-07-07T12:18:25.887-03:00",
        "plazo": "24hs",
        "moneda": "ARS",
        "precio": 129500.0,
        "nominales": 65406,
        "lado": "COMPRA"
      },
      {
        "fecha_hora": "2026-07-07T11:51:31.765-03:00",
        "plazo": "24hs",
        "moneda": "ARS",
        "precio": 129500.0,
        "nominales": 43076,
        "lado": "COMPRA"
      },
      {
        "fecha_hora": "2026-07-07T12:07:30.456-03:00",
        "plazo": "24hs",
        "moneda": "ARS",
        "precio": 129500.0,
        "nominales": 43000,
        "lado": "COMPRA"
      },
      {
        "fecha_hora": "2026-07-07T12:07:38.884-03:00",
        "plazo": "24hs",
        "moneda": "ARS",
        "precio": 129500.0,
        "nominales": 43000,
        "lado": "COMPRA"
      },
      {
        "fecha_hora": "2026-07-07T11:45:31.739-03:00",
        "plazo": "24hs",
        "moneda": "ARS",
        "precio": 128420.0,
        "nominales": 30831,
        "lado": "VENTA"
      },
      {
        "fecha_hora": "2026-07-07T10:45:36.726-03:00",
        "plazo": "24hs",
        "moneda": "ARS",
        "precio": 128500.0,
        "nominales": 30000,
        "lado": "COMPRA"
      },
      {
        "fecha_hora": "2026-07-07T11:51:36.463-03:00",
        "plazo": "24hs",
        "moneda": "ARS",
        "precio": 129500.0,
        "nominales": 29076,
        "lado": "COMPRA"
      },
      {
        "fecha_hora": "2026-07-07T12:58:22.809-03:00",
        "plazo": "24hs",
        "moneda": "ARS",
        "precio": 129600.0,
        "nominales": 27245,
        "lado": "COMPRA"
      },
      {
        "fecha_hora": "2026-07-07T12:33:45.132-03:00",
        "plazo": "24hs",
        "moneda": "ARS",
        "precio": 129500.0,
        "nominales": 13594,
        "lado": "COMPRA"
      }
    ],
    "NPCDD": [
      {
        "fecha_hora": "2026-07-07T15:30:18.77-03:00",
        "plazo": "24hs",
        "moneda": "USD",
        "precio": 100.5,
        "nominales": 29336,
        "lado": "VENTA"
      },
      {
        "fecha_hora": "2026-07-07T15:30:18.766-03:00",
        "plazo": "24hs",
        "moneda": "USD",
        "precio": 100.5,
        "nominales": 19161,
        "lado": "VENTA"
      },
      {
        "fecha_hora": "2026-07-07T12:52:05.941-03:00",
        "plazo": "24hs",
        "moneda": "USD",
        "precio": 100.5,
        "nominales": 12700,
        "lado": "VENTA"
      },
      {
        "fecha_hora": "2026-07-07T16:18:50.067-03:00",
        "plazo": "24hs",
        "moneda": "USD",
        "precio": 100.8,
        "nominales": 10912,
        "lado": "VENTA"
      }
    ],
    "NPCDO": [
      {
        "fecha_hora": "2026-07-07T16:18:49.662-03:00",
        "plazo": "24hs",
        "moneda": "ARS",
        "precio": 153980.0,
        "nominales": 10912,
        "lado": "COMPRA"
      }
    ],
    "OLC6D": [
      {
        "fecha_hora": "2026-07-07T11:24:24.755-03:00",
        "plazo": "24hs",
        "moneda": "USD",
        "precio": 106.2,
        "nominales": 75000,
        "lado": "VENTA"
      },
      {
        "fecha_hora": "2026-07-07T11:24:51.831-03:00",
        "plazo": "24hs",
        "moneda": "USD",
        "precio": 106.2,
        "nominales": 50000,
        "lado": "VENTA"
      },
      {
        "fecha_hora": "2026-07-07T11:39:31.676-03:00",
        "plazo": "24hs",
        "moneda": "USD",
        "precio": 106.0,
        "nominales": 10000,
        "lado": "DESCONOCIDO"
      }
    ],
    "OLC7D": [
      {
        "fecha_hora": "2026-07-07T16:33:25.331-03:00",
        "plazo": "24hs",
        "moneda": "USD",
        "precio": 105.35,
        "nominales": 12422,
        "lado": "VENTA"
      }
    ],
    "OLC7O": [
      {
        "fecha_hora": "2026-07-07T16:33:25.361-03:00",
        "plazo": "24hs",
        "moneda": "ARS",
        "precio": 161200.0,
        "nominales": 12422,
        "lado": "VENTA"
      }
    ],
    "OTS2D": [
      {
        "fecha_hora": "2026-07-07T11:35:43.926-03:00",
        "plazo": "24hs",
        "moneda": "USD",
        "precio": 103.1,
        "nominales": 25000,
        "lado": "VENTA"
      }
    ],
    "PLC2D": [
      {
        "fecha_hora": "2026-07-07T12:04:20.117-03:00",
        "plazo": "24hs",
        "moneda": "USD",
        "precio": 106.65,
        "nominales": 150000,
        "lado": "VENTA"
      },
      {
        "fecha_hora": "2026-07-07T12:04:24.347-03:00",
        "plazo": "24hs",
        "moneda": "USD",
        "precio": 106.55,
        "nominales": 150000,
        "lado": "VENTA"
      },
      {
        "fecha_hora": "2026-07-07T12:04:27.826-03:00",
        "plazo": "24hs",
        "moneda": "USD",
        "precio": 106.55,
        "nominales": 150000,
        "lado": "VENTA"
      },
      {
        "fecha_hora": "2026-07-07T12:04:29.992-03:00",
        "plazo": "24hs",
        "moneda": "USD",
        "precio": 106.55,
        "nominales": 150000,
        "lado": "VENTA"
      },
      {
        "fecha_hora": "2026-07-07T12:24:32.257-03:00",
        "plazo": "24hs",
        "moneda": "USD",
        "precio": 106.6,
        "nominales": 36741,
        "lado": "COMPRA"
      },
      {
        "fecha_hora": "2026-07-07T12:24:32.264-03:00",
        "plazo": "24hs",
        "moneda": "USD",
        "precio": 106.6,
        "nominales": 36741,
        "lado": "COMPRA"
      },
      {
        "fecha_hora": "2026-07-07T12:24:32.268-03:00",
        "plazo": "24hs",
        "moneda": "USD",
        "precio": 106.6,
        "nominales": 34852,
        "lado": "COMPRA"
      },
      {
        "fecha_hora": "2026-07-07T12:24:32.251-03:00",
        "plazo": "24hs",
        "moneda": "USD",
        "precio": 106.6,
        "nominales": 29212,
        "lado": "COMPRA"
      }
    ],
    "PLC4D": [
      {
        "fecha_hora": "2026-07-07T11:24:42.761-03:00",
        "plazo": "24hs",
        "moneda": "USD",
        "precio": 108.65,
        "nominales": 11000,
        "lado": "COMPRA"
      },
      {
        "fecha_hora": "2026-07-07T11:10:55.368-03:00",
        "plazo": "24hs",
        "moneda": "USD",
        "precio": 108.7,
        "nominales": 10000,
        "lado": "COMPRA"
      },
      {
        "fecha_hora": "2026-07-07T11:22:11.437-03:00",
        "plazo": "24hs",
        "moneda": "USD",
        "precio": 108.7,
        "nominales": 10000,
        "lado": "COMPRA"
      },
      {
        "fecha_hora": "2026-07-07T11:27:30.367-03:00",
        "plazo": "24hs",
        "moneda": "USD",
        "precio": 108.65,
        "nominales": 10000,
        "lado": "COMPRA"
      },
      {
        "fecha_hora": "2026-07-07T12:40:55.292-03:00",
        "plazo": "24hs",
        "moneda": "USD",
        "precio": 108.6,
        "nominales": 10000,
        "lado": "VENTA"
      }
    ],
    "PLC6D": [
      {
        "fecha_hora": "2026-07-07T16:15:53.627-03:00",
        "plazo": "24hs",
        "moneda": "USD",
        "precio": 106.35,
        "nominales": 13165,
        "lado": "COMPRA"
      },
      {
        "fecha_hora": "2026-07-07T16:15:52.549-03:00",
        "plazo": "24hs",
        "moneda": "USD",
        "precio": 106.35,
        "nominales": 12311,
        "lado": "VENTA"
      },
      {
        "fecha_hora": "2026-07-07T16:15:55.127-03:00",
        "plazo": "24hs",
        "moneda": "USD",
        "precio": 106.35,
        "nominales": 10068,
        "lado": "COMPRA"
      }
    ],
    "PLC6O": [
      {
        "fecha_hora": "2026-07-07T16:15:52.615-03:00",
        "plazo": "24hs",
        "moneda": "ARS",
        "precio": 163000.0,
        "nominales": 12311,
        "lado": "VENTA"
      },
      {
        "fecha_hora": "2026-07-07T16:15:53.696-03:00",
        "plazo": "24hs",
        "moneda": "ARS",
        "precio": 163000.0,
        "nominales": 11212,
        "lado": "VENTA"
      }
    ],
    "PLC7D": [
      {
        "fecha_hora": "2026-07-07T16:28:54.931-03:00",
        "plazo": "24hs",
        "moneda": "USD",
        "precio": 101.1,
        "nominales": 440000,
        "lado": "COMPRA"
      },
      {
        "fecha_hora": "2026-07-07T10:41:36.468-03:00",
        "plazo": "24hs",
        "moneda": "USD",
        "precio": 101.3,
        "nominales": 31000,
        "lado": "COMPRA"
      },
      {
        "fecha_hora": "2026-07-07T10:41:36.471-03:00",
        "plazo": "24hs",
        "moneda": "USD",
        "precio": 101.3,
        "nominales": 30000,
        "lado": "COMPRA"
      },
      {
        "fecha_hora": "2026-07-07T15:50:05.386-03:00",
        "plazo": "24hs",
        "moneda": "USD",
        "precio": 101.1,
        "nominales": 29000,
        "lado": "COMPRA"
      },
      {
        "fecha_hora": "2026-07-07T15:17:58.791-03:00",
        "plazo": "24hs",
        "moneda": "USD",
        "precio": 101.05,
        "nominales": 26000,
        "lado": "VENTA"
      },
      {
        "fecha_hora": "2026-07-07T11:04:03.545-03:00",
        "plazo": "24hs",
        "moneda": "USD",
        "precio": 101.0,
        "nominales": 21000,
        "lado": "VENTA"
      },
      {
        "fecha_hora": "2026-07-07T15:14:15.613-03:00",
        "plazo": "24hs",
        "moneda": "USD",
        "precio": 101.05,
        "nominales": 21000,
        "lado": "VENTA"
      },
      {
        "fecha_hora": "2026-07-07T16:47:15.543-03:00",
        "plazo": "24hs",
        "moneda": "USD",
        "precio": 101.35,
        "nominales": 20000,
        "lado": "COMPRA"
      },
      {
        "fecha_hora": "2026-07-07T10:49:32.637-03:00",
        "plazo": "24hs",
        "moneda": "USD",
        "precio": 101.15,
        "nominales": 19000,
        "lado": "COMPRA"
      },
      {
        "fecha_hora": "2026-07-07T11:20:40.466-03:00",
        "plazo": "24hs",
        "moneda": "USD",
        "precio": 101.05,
        "nominales": 19000,
        "lado": "COMPRA"
      },
      {
        "fecha_hora": "2026-07-07T12:21:32.968-03:00",
        "plazo": "24hs",
        "moneda": "USD",
        "precio": 101.0,
        "nominales": 18000,
        "lado": "VENTA"
      },
      {
        "fecha_hora": "2026-07-07T11:50:00.199-03:00",
        "plazo": "24hs",
        "moneda": "USD",
        "precio": 100.95,
        "nominales": 15000,
        "lado": "VENTA"
      },
      {
        "fecha_hora": "2026-07-07T11:10:58.109-03:00",
        "plazo": "24hs",
        "moneda": "USD",
        "precio": 101.0,
        "nominales": 14000,
        "lado": "VENTA"
      },
      {
        "fecha_hora": "2026-07-07T11:21:53.783-03:00",
        "plazo": "24hs",
        "moneda": "USD",
        "precio": 101.05,
        "nominales": 14000,
        "lado": "COMPRA"
      },
      {
        "fecha_hora": "2026-07-07T10:41:19.534-03:00",
        "plazo": "24hs",
        "moneda": "USD",
        "precio": 101.3,
        "nominales": 13000,
        "lado": "COMPRA"
      },
      {
        "fecha_hora": "2026-07-07T10:41:36.474-03:00",
        "plazo": "24hs",
        "moneda": "USD",
        "precio": 101.3,
        "nominales": 11000,
        "lado": "COMPRA"
      },
      {
        "fecha_hora": "2026-07-07T11:04:03.543-03:00",
        "plazo": "24hs",
        "moneda": "USD",
        "precio": 101.0,
        "nominales": 11000,
        "lado": "VENTA"
      },
      {
        "fecha_hora": "2026-07-07T11:04:03.541-03:00",
        "plazo": "24hs",
        "moneda": "USD",
        "precio": 101.0,
        "nominales": 10000,
        "lado": "VENTA"
      },
      {
        "fecha_hora": "2026-07-07T12:30:15.708-03:00",
        "plazo": "24hs",
        "moneda": "USD",
        "precio": 101.05,
        "nominales": 10000,
        "lado": "COMPRA"
      },
      {
        "fecha_hora": "2026-07-07T12:42:28.592-03:00",
        "plazo": "24hs",
        "moneda": "USD",
        "precio": 101.05,
        "nominales": 10000,
        "lado": "COMPRA"
      },
      {
        "fecha_hora": "2026-07-07T16:28:54.931-03:00",
        "plazo": "24hs",
        "moneda": "USD",
        "precio": 101.1,
        "nominales": 10000,
        "lado": "COMPRA"
      }
    ],
    "PLC7O": [
      {
        "fecha_hora": "2026-07-07T12:59:37.304-03:00",
        "plazo": "CI",
        "moneda": "ARS",
        "precio": 154430.0,
        "nominales": 25000,
        "lado": "COMPRA"
      },
      {
        "fecha_hora": "2026-07-07T12:33:02.455-03:00",
        "plazo": "24hs",
        "moneda": "ARS",
        "precio": 154630.0,
        "nominales": 19000,
        "lado": "COMPRA"
      },
      {
        "fecha_hora": "2026-07-07T16:12:45.529-03:00",
        "plazo": "24hs",
        "moneda": "ARS",
        "precio": 154990.0,
        "nominales": 18000,
        "lado": "COMPRA"
      },
      {
        "fecha_hora": "2026-07-07T13:00:00.466-03:00",
        "plazo": "24hs",
        "moneda": "ARS",
        "precio": 154420.0,
        "nominales": 16000,
        "lado": "VENTA"
      },
      {
        "fecha_hora": "2026-07-07T16:46:37.317-03:00",
        "plazo": "24hs",
        "moneda": "ARS",
        "precio": 154800.0,
        "nominales": 15000,
        "lado": "COMPRA"
      },
      {
        "fecha_hora": "2026-07-07T11:46:19.579-03:00",
        "plazo": "24hs",
        "moneda": "ARS",
        "precio": 154530.0,
        "nominales": 10000,
        "lado": "COMPRA"
      },
      {
        "fecha_hora": "2026-07-07T12:41:24.982-03:00",
        "plazo": "24hs",
        "moneda": "ARS",
        "precio": 154630.0,
        "nominales": 10000,
        "lado": "COMPRA"
      },
      {
        "fecha_hora": "2026-07-07T14:03:45.29-03:00",
        "plazo": "24hs",
        "moneda": "ARS",
        "precio": 154470.0,
        "nominales": 10000,
        "lado": "COMPRA"
      },
      {
        "fecha_hora": "2026-07-07T15:17:14.365-03:00",
        "plazo": "24hs",
        "moneda": "ARS",
        "precio": 154430.0,
        "nominales": 10000,
        "lado": "COMPRA"
      },
      {
        "fecha_hora": "2026-07-07T16:12:51.539-03:00",
        "plazo": "24hs",
        "moneda": "ARS",
        "precio": 154990.0,
        "nominales": 10000,
        "lado": "COMPRA"
      }
    ],
    "PN35D": [
      {
        "fecha_hora": "2026-07-07T11:59:10.984-03:00",
        "plazo": "24hs",
        "moneda": "USD",
        "precio": 107.15,
        "nominales": 29295,
        "lado": "VENTA"
      },
      {
        "fecha_hora": "2026-07-07T11:57:24.193-03:00",
        "plazo": "24hs",
        "moneda": "USD",
        "precio": 107.15,
        "nominales": 10000,
        "lado": "VENTA"
      }
    ],
    "PN41D": [
      {
        "fecha_hora": "2026-07-07T16:26:16.391-03:00",
        "plazo": "24hs",
        "moneda": "USD",
        "precio": 108.55,
        "nominales": 15000,
        "lado": "VENTA"
      }
    ],
    "PNXCO": [
      {
        "fecha_hora": "2026-07-07T15:45:20.711-03:00",
        "plazo": "24hs",
        "moneda": "ARS",
        "precio": 171600.0,
        "nominales": 14000,
        "lado": "VENTA"
      }
    ],
    "PQCRD": [
      {
        "fecha_hora": "2026-07-07T12:40:09.255-03:00",
        "plazo": "24hs",
        "moneda": "USD",
        "precio": 100.5,
        "nominales": 48600,
        "lado": "COMPRA"
      }
    ],
    "RC1CD": [
      {
        "fecha_hora": "2026-07-07T15:49:20.616-03:00",
        "plazo": "24hs",
        "moneda": "USD",
        "precio": 110.8,
        "nominales": 18000,
        "lado": "COMPRA"
      },
      {
        "fecha_hora": "2026-07-07T15:57:24.764-03:00",
        "plazo": "24hs",
        "moneda": "USD",
        "precio": 110.75,
        "nominales": 15000,
        "lado": "COMPRA"
      },
      {
        "fecha_hora": "2026-07-07T15:52:21.533-03:00",
        "plazo": "24hs",
        "moneda": "USD",
        "precio": 110.8,
        "nominales": 11000,
        "lado": "COMPRA"
      }
    ],
    "RC1CO": [
      {
        "fecha_hora": "2026-07-07T14:01:16.594-03:00",
        "plazo": "24hs",
        "moneda": "ARS",
        "precio": 170400.0,
        "nominales": 18000,
        "lado": "VENTA"
      }
    ],
    "RUCDD": [
      {
        "fecha_hora": "2026-07-07T12:34:45.886-03:00",
        "plazo": "24hs",
        "moneda": "USD",
        "precio": 109.0,
        "nominales": 15000,
        "lado": "COMPRA"
      }
    ],
    "SBC1D": [
      {
        "fecha_hora": "2026-07-07T11:32:35.47-03:00",
        "plazo": "24hs",
        "moneda": "USD",
        "precio": 73.25,
        "nominales": 11009,
        "lado": "VENTA"
      }
    ],
    "T641D": [
      {
        "fecha_hora": "2026-07-07T17:00:03.39-03:00",
        "plazo": "24hs",
        "moneda": "USD",
        "precio": 103.8,
        "nominales": 75000,
        "lado": "COMPRA"
      }
    ],
    "TLCMD": [
      {
        "fecha_hora": "2026-07-07T12:14:58.633-03:00",
        "plazo": "24hs",
        "moneda": "USD",
        "precio": 116.6,
        "nominales": 17000,
        "lado": "COMPRA"
      },
      {
        "fecha_hora": "2026-07-07T12:34:00.7-03:00",
        "plazo": "24hs",
        "moneda": "USD",
        "precio": 116.4,
        "nominales": 16000,
        "lado": "VENTA"
      },
      {
        "fecha_hora": "2026-07-07T12:05:50.328-03:00",
        "plazo": "24hs",
        "moneda": "USD",
        "precio": 116.5,
        "nominales": 14000,
        "lado": "COMPRA"
      },
      {
        "fecha_hora": "2026-07-07T13:58:06.009-03:00",
        "plazo": "24hs",
        "moneda": "USD",
        "precio": 116.3,
        "nominales": 10000,
        "lado": "VENTA"
      },
      {
        "fecha_hora": "2026-07-07T13:58:06.025-03:00",
        "plazo": "24hs",
        "moneda": "USD",
        "precio": 116.3,
        "nominales": 10000,
        "lado": "VENTA"
      }
    ],
    "TLCMO": [
      {
        "fecha_hora": "2026-07-07T12:31:12.005-03:00",
        "plazo": "24hs",
        "moneda": "ARS",
        "precio": 177870.0,
        "nominales": 20000,
        "lado": "VENTA"
      }
    ],
    "TLCOO": [
      {
        "fecha_hora": "2026-07-07T15:41:19.516-03:00",
        "plazo": "24hs",
        "moneda": "ARS",
        "precio": 159400.0,
        "nominales": 10719,
        "lado": "VENTA"
      }
    ],
    "TLCPD": [
      {
        "fecha_hora": "2026-07-07T11:37:05.295-03:00",
        "plazo": "24hs",
        "moneda": "USD",
        "precio": 111.85,
        "nominales": 27942,
        "lado": "COMPRA"
      },
      {
        "fecha_hora": "2026-07-07T11:06:53.739-03:00",
        "plazo": "24hs",
        "moneda": "USD",
        "precio": 111.85,
        "nominales": 23911,
        "lado": "COMPRA"
      },
      {
        "fecha_hora": "2026-07-07T12:25:57.213-03:00",
        "plazo": "24hs",
        "moneda": "USD",
        "precio": 111.8,
        "nominales": 14000,
        "lado": "COMPRA"
      },
      {
        "fecha_hora": "2026-07-07T12:32:40.417-03:00",
        "plazo": "CI",
        "moneda": "USD",
        "precio": 111.8,
        "nominales": 13189,
        "lado": "COMPRA"
      },
      {
        "fecha_hora": "2026-07-07T12:09:02.107-03:00",
        "plazo": "24hs",
        "moneda": "USD",
        "precio": 111.7,
        "nominales": 12622,
        "lado": "VENTA"
      }
    ],
    "TLCPO": [
      {
        "fecha_hora": "2026-07-07T11:37:05.288-03:00",
        "plazo": "24hs",
        "moneda": "ARS",
        "precio": 170910.0,
        "nominales": 28533,
        "lado": "COMPRA"
      },
      {
        "fecha_hora": "2026-07-07T10:56:11.506-03:00",
        "plazo": "24hs",
        "moneda": "ARS",
        "precio": 171470.0,
        "nominales": 20444,
        "lado": "VENTA"
      },
      {
        "fecha_hora": "2026-07-07T11:35:00.236-03:00",
        "plazo": "24hs",
        "moneda": "ARS",
        "precio": 170750.0,
        "nominales": 18820,
        "lado": "COMPRA"
      },
      {
        "fecha_hora": "2026-07-07T11:37:05.335-03:00",
        "plazo": "24hs",
        "moneda": "ARS",
        "precio": 170910.0,
        "nominales": 18172,
        "lado": "COMPRA"
      },
      {
        "fecha_hora": "2026-07-07T10:59:05.272-03:00",
        "plazo": "24hs",
        "moneda": "ARS",
        "precio": 170980.0,
        "nominales": 16252,
        "lado": "VENTA"
      },
      {
        "fecha_hora": "2026-07-07T16:24:50.3-03:00",
        "plazo": "24hs",
        "moneda": "ARS",
        "precio": 170600.0,
        "nominales": 10223,
        "lado": "COMPRA"
      }
    ],
    "TLCTD": [
      {
        "fecha_hora": "2026-07-07T11:23:08.509-03:00",
        "plazo": "24hs",
        "moneda": "USD",
        "precio": 111.65,
        "nominales": 10000,
        "lado": "VENTA"
      }
    ],
    "TLCUD": [
      {
        "fecha_hora": "2026-07-07T12:20:30.902-03:00",
        "plazo": "24hs",
        "moneda": "USD",
        "precio": 104.35,
        "nominales": 16000,
        "lado": "VENTA"
      }
    ],
    "TSC3D": [
      {
        "fecha_hora": "2026-07-07T12:02:40.326-03:00",
        "plazo": "24hs",
        "moneda": "USD",
        "precio": 113.1,
        "nominales": 30000,
        "lado": "COMPRA"
      },
      {
        "fecha_hora": "2026-07-07T11:39:20.659-03:00",
        "plazo": "24hs",
        "moneda": "USD",
        "precio": 112.85,
        "nominales": 15000,
        "lado": "VENTA"
      },
      {
        "fecha_hora": "2026-07-07T11:39:23.483-03:00",
        "plazo": "24hs",
        "moneda": "USD",
        "precio": 112.85,
        "nominales": 10000,
        "lado": "VENTA"
      },
      {
        "fecha_hora": "2026-07-07T11:50:04.247-03:00",
        "plazo": "24hs",
        "moneda": "USD",
        "precio": 112.85,
        "nominales": 10000,
        "lado": "VENTA"
      },
      {
        "fecha_hora": "2026-07-07T11:50:04.457-03:00",
        "plazo": "24hs",
        "moneda": "USD",
        "precio": 112.85,
        "nominales": 10000,
        "lado": "VENTA"
      },
      {
        "fecha_hora": "2026-07-07T11:50:04.757-03:00",
        "plazo": "24hs",
        "moneda": "USD",
        "precio": 112.85,
        "nominales": 10000,
        "lado": "VENTA"
      },
      {
        "fecha_hora": "2026-07-07T11:56:03.076-03:00",
        "plazo": "24hs",
        "moneda": "USD",
        "precio": 112.9,
        "nominales": 10000,
        "lado": "VENTA"
      },
      {
        "fecha_hora": "2026-07-07T11:56:27.152-03:00",
        "plazo": "24hs",
        "moneda": "USD",
        "precio": 112.9,
        "nominales": 10000,
        "lado": "VENTA"
      },
      {
        "fecha_hora": "2026-07-07T11:59:14.515-03:00",
        "plazo": "24hs",
        "moneda": "USD",
        "precio": 113.0,
        "nominales": 10000,
        "lado": "COMPRA"
      },
      {
        "fecha_hora": "2026-07-07T11:59:17.049-03:00",
        "plazo": "24hs",
        "moneda": "USD",
        "precio": 113.0,
        "nominales": 10000,
        "lado": "COMPRA"
      },
      {
        "fecha_hora": "2026-07-07T11:59:19.482-03:00",
        "plazo": "24hs",
        "moneda": "USD",
        "precio": 113.0,
        "nominales": 10000,
        "lado": "COMPRA"
      },
      {
        "fecha_hora": "2026-07-07T11:59:51.132-03:00",
        "plazo": "24hs",
        "moneda": "USD",
        "precio": 113.0,
        "nominales": 10000,
        "lado": "COMPRA"
      },
      {
        "fecha_hora": "2026-07-07T11:59:56.241-03:00",
        "plazo": "24hs",
        "moneda": "USD",
        "precio": 113.0,
        "nominales": 10000,
        "lado": "VENTA"
      },
      {
        "fecha_hora": "2026-07-07T12:00:03.082-03:00",
        "plazo": "24hs",
        "moneda": "USD",
        "precio": 113.0,
        "nominales": 10000,
        "lado": "VENTA"
      },
      {
        "fecha_hora": "2026-07-07T12:00:11.115-03:00",
        "plazo": "24hs",
        "moneda": "USD",
        "precio": 113.0,
        "nominales": 10000,
        "lado": "VENTA"
      },
      {
        "fecha_hora": "2026-07-07T12:02:40.326-03:00",
        "plazo": "24hs",
        "moneda": "USD",
        "precio": 113.1,
        "nominales": 10000,
        "lado": "COMPRA"
      },
      {
        "fecha_hora": "2026-07-07T12:19:27.106-03:00",
        "plazo": "24hs",
        "moneda": "USD",
        "precio": 113.1,
        "nominales": 10000,
        "lado": "COMPRA"
      },
      {
        "fecha_hora": "2026-07-07T12:35:36.875-03:00",
        "plazo": "CI",
        "moneda": "USD",
        "precio": 112.85,
        "nominales": 10000,
        "lado": "VENTA"
      },
      {
        "fecha_hora": "2026-07-07T13:57:03.87-03:00",
        "plazo": "24hs",
        "moneda": "USD",
        "precio": 113.0,
        "nominales": 10000,
        "lado": "VENTA"
      },
      {
        "fecha_hora": "2026-07-07T15:36:39.745-03:00",
        "plazo": "24hs",
        "moneda": "USD",
        "precio": 113.0,
        "nominales": 10000,
        "lado": "VENTA"
      },
      {
        "fecha_hora": "2026-07-07T15:46:12.586-03:00",
        "plazo": "24hs",
        "moneda": "USD",
        "precio": 113.0,
        "nominales": 10000,
        "lado": "VENTA"
      },
      {
        "fecha_hora": "2026-07-07T15:59:14.199-03:00",
        "plazo": "24hs",
        "moneda": "USD",
        "precio": 113.0,
        "nominales": 10000,
        "lado": "VENTA"
      },
      {
        "fecha_hora": "2026-07-07T15:59:20.176-03:00",
        "plazo": "24hs",
        "moneda": "USD",
        "precio": 113.0,
        "nominales": 10000,
        "lado": "VENTA"
      },
      {
        "fecha_hora": "2026-07-07T15:59:04.148-03:00",
        "plazo": "24hs",
        "moneda": "USD",
        "precio": 113.0,
        "nominales": 10000,
        "lado": "VENTA"
      },
      {
        "fecha_hora": "2026-07-07T15:59:20.873-03:00",
        "plazo": "24hs",
        "moneda": "USD",
        "precio": 113.0,
        "nominales": 10000,
        "lado": "VENTA"
      },
      {
        "fecha_hora": "2026-07-07T15:59:21.689-03:00",
        "plazo": "24hs",
        "moneda": "USD",
        "precio": 113.0,
        "nominales": 10000,
        "lado": "VENTA"
      },
      {
        "fecha_hora": "2026-07-07T15:59:22.609-03:00",
        "plazo": "24hs",
        "moneda": "USD",
        "precio": 113.0,
        "nominales": 10000,
        "lado": "VENTA"
      },
      {
        "fecha_hora": "2026-07-07T16:00:05.173-03:00",
        "plazo": "24hs",
        "moneda": "USD",
        "precio": 113.0,
        "nominales": 10000,
        "lado": "VENTA"
      },
      {
        "fecha_hora": "2026-07-07T16:00:05.874-03:00",
        "plazo": "24hs",
        "moneda": "USD",
        "precio": 113.0,
        "nominales": 10000,
        "lado": "VENTA"
      },
      {
        "fecha_hora": "2026-07-07T16:00:07.206-03:00",
        "plazo": "24hs",
        "moneda": "USD",
        "precio": 113.0,
        "nominales": 10000,
        "lado": "VENTA"
      },
      {
        "fecha_hora": "2026-07-07T16:00:07.821-03:00",
        "plazo": "24hs",
        "moneda": "USD",
        "precio": 113.0,
        "nominales": 10000,
        "lado": "VENTA"
      },
      {
        "fecha_hora": "2026-07-07T16:00:43.067-03:00",
        "plazo": "24hs",
        "moneda": "USD",
        "precio": 113.0,
        "nominales": 10000,
        "lado": "VENTA"
      },
      {
        "fecha_hora": "2026-07-07T16:04:50.524-03:00",
        "plazo": "24hs",
        "moneda": "USD",
        "precio": 113.0,
        "nominales": 10000,
        "lado": "VENTA"
      },
      {
        "fecha_hora": "2026-07-07T16:10:05.128-03:00",
        "plazo": "24hs",
        "moneda": "USD",
        "precio": 113.0,
        "nominales": 10000,
        "lado": "VENTA"
      },
      {
        "fecha_hora": "2026-07-07T16:10:12.288-03:00",
        "plazo": "24hs",
        "moneda": "USD",
        "precio": 113.0,
        "nominales": 10000,
        "lado": "VENTA"
      },
      {
        "fecha_hora": "2026-07-07T16:10:15.506-03:00",
        "plazo": "24hs",
        "moneda": "USD",
        "precio": 113.0,
        "nominales": 10000,
        "lado": "VENTA"
      },
      {
        "fecha_hora": "2026-07-07T16:12:53.584-03:00",
        "plazo": "24hs",
        "moneda": "USD",
        "precio": 113.0,
        "nominales": 10000,
        "lado": "VENTA"
      }
    ],
    "TSC3O": [
      {
        "fecha_hora": "2026-07-07T11:32:49.87-03:00",
        "plazo": "24hs",
        "moneda": "ARS",
        "precio": 172300.0,
        "nominales": 50000,
        "lado": "DESCONOCIDO"
      },
      {
        "fecha_hora": "2026-07-07T11:33:27.685-03:00",
        "plazo": "24hs",
        "moneda": "ARS",
        "precio": 172350.0,
        "nominales": 41000,
        "lado": "DESCONOCIDO"
      },
      {
        "fecha_hora": "2026-07-07T11:40:25.556-03:00",
        "plazo": "24hs",
        "moneda": "ARS",
        "precio": 172350.0,
        "nominales": 40000,
        "lado": "COMPRA"
      },
      {
        "fecha_hora": "2026-07-07T11:45:55.454-03:00",
        "plazo": "24hs",
        "moneda": "ARS",
        "precio": 172300.0,
        "nominales": 40000,
        "lado": "COMPRA"
      },
      {
        "fecha_hora": "2026-07-07T11:46:30.422-03:00",
        "plazo": "24hs",
        "moneda": "ARS",
        "precio": 172400.0,
        "nominales": 40000,
        "lado": "COMPRA"
      },
      {
        "fecha_hora": "2026-07-07T11:38:14.962-03:00",
        "plazo": "24hs",
        "moneda": "ARS",
        "precio": 172150.0,
        "nominales": 30000,
        "lado": "VENTA"
      },
      {
        "fecha_hora": "2026-07-07T16:10:10.275-03:00",
        "plazo": "24hs",
        "moneda": "ARS",
        "precio": 172450.0,
        "nominales": 30000,
        "lado": "COMPRA"
      },
      {
        "fecha_hora": "2026-07-07T11:34:33.561-03:00",
        "plazo": "24hs",
        "moneda": "ARS",
        "precio": 172250.0,
        "nominales": 29000,
        "lado": "DESCONOCIDO"
      },
      {
        "fecha_hora": "2026-07-07T11:39:20.522-03:00",
        "plazo": "24hs",
        "moneda": "ARS",
        "precio": 172200.0,
        "nominales": 20000,
        "lado": "COMPRA"
      },
      {
        "fecha_hora": "2026-07-07T11:34:34.27-03:00",
        "plazo": "24hs",
        "moneda": "ARS",
        "precio": 172250.0,
        "nominales": 15000,
        "lado": "COMPRA"
      },
      {
        "fecha_hora": "2026-07-07T11:07:13.653-03:00",
        "plazo": "24hs",
        "moneda": "ARS",
        "precio": 172250.0,
        "nominales": 10000,
        "lado": "VENTA"
      },
      {
        "fecha_hora": "2026-07-07T11:39:20.488-03:00",
        "plazo": "24hs",
        "moneda": "ARS",
        "precio": 172200.0,
        "nominales": 10000,
        "lado": "COMPRA"
      },
      {
        "fecha_hora": "2026-07-07T11:39:20.534-03:00",
        "plazo": "24hs",
        "moneda": "ARS",
        "precio": 172200.0,
        "nominales": 10000,
        "lado": "COMPRA"
      },
      {
        "fecha_hora": "2026-07-07T15:59:16.969-03:00",
        "plazo": "24hs",
        "moneda": "ARS",
        "precio": 172450.0,
        "nominales": 10000,
        "lado": "COMPRA"
      },
      {
        "fecha_hora": "2026-07-07T15:59:20.036-03:00",
        "plazo": "24hs",
        "moneda": "ARS",
        "precio": 172450.0,
        "nominales": 10000,
        "lado": "COMPRA"
      },
      {
        "fecha_hora": "2026-07-07T15:59:20.729-03:00",
        "plazo": "24hs",
        "moneda": "ARS",
        "precio": 172450.0,
        "nominales": 10000,
        "lado": "COMPRA"
      },
      {
        "fecha_hora": "2026-07-07T15:59:21.549-03:00",
        "plazo": "24hs",
        "moneda": "ARS",
        "precio": 172450.0,
        "nominales": 10000,
        "lado": "COMPRA"
      },
      {
        "fecha_hora": "2026-07-07T15:59:10.355-03:00",
        "plazo": "24hs",
        "moneda": "ARS",
        "precio": 172450.0,
        "nominales": 10000,
        "lado": "COMPRA"
      },
      {
        "fecha_hora": "2026-07-07T16:00:04.966-03:00",
        "plazo": "24hs",
        "moneda": "ARS",
        "precio": 172450.0,
        "nominales": 10000,
        "lado": "COMPRA"
      },
      {
        "fecha_hora": "2026-07-07T16:00:05.678-03:00",
        "plazo": "24hs",
        "moneda": "ARS",
        "precio": 172450.0,
        "nominales": 10000,
        "lado": "COMPRA"
      },
      {
        "fecha_hora": "2026-07-07T16:00:06.376-03:00",
        "plazo": "24hs",
        "moneda": "ARS",
        "precio": 172450.0,
        "nominales": 10000,
        "lado": "COMPRA"
      },
      {
        "fecha_hora": "2026-07-07T16:00:07.012-03:00",
        "plazo": "24hs",
        "moneda": "ARS",
        "precio": 172450.0,
        "nominales": 10000,
        "lado": "COMPRA"
      },
      {
        "fecha_hora": "2026-07-07T16:00:07.6-03:00",
        "plazo": "24hs",
        "moneda": "ARS",
        "precio": 172450.0,
        "nominales": 10000,
        "lado": "COMPRA"
      },
      {
        "fecha_hora": "2026-07-07T16:04:50.375-03:00",
        "plazo": "24hs",
        "moneda": "ARS",
        "precio": 172450.0,
        "nominales": 10000,
        "lado": "COMPRA"
      },
      {
        "fecha_hora": "2026-07-07T16:10:10.269-03:00",
        "plazo": "24hs",
        "moneda": "ARS",
        "precio": 172450.0,
        "nominales": 10000,
        "lado": "COMPRA"
      }
    ],
    "TSC4D": [
      {
        "fecha_hora": "2026-07-07T12:36:27.546-03:00",
        "plazo": "24hs",
        "moneda": "USD",
        "precio": 107.7,
        "nominales": 12000,
        "lado": "VENTA"
      },
      {
        "fecha_hora": "2026-07-07T11:47:54.353-03:00",
        "plazo": "24hs",
        "moneda": "USD",
        "precio": 107.7,
        "nominales": 10000,
        "lado": "COMPRA"
      }
    ],
    "TSC4O": [
      {
        "fecha_hora": "2026-07-07T16:14:06.483-03:00",
        "plazo": "24hs",
        "moneda": "ARS",
        "precio": 165050.0,
        "nominales": 10000,
        "lado": "COMPRA"
      },
      {
        "fecha_hora": "2026-07-07T16:45:15.303-03:00",
        "plazo": "24hs",
        "moneda": "ARS",
        "precio": 164300.0,
        "nominales": 10000,
        "lado": "COMPRA"
      }
    ],
    "VBC2D": [
      {
        "fecha_hora": "2026-07-07T12:27:22.431-03:00",
        "plazo": "CI",
        "moneda": "USD",
        "precio": 102.7,
        "nominales": 20694,
        "lado": "VENTA"
      }
    ],
    "VBC2O": [
      {
        "fecha_hora": "2026-07-07T12:17:52.594-03:00",
        "plazo": "CI",
        "moneda": "ARS",
        "precio": 156630.0,
        "nominales": 19222,
        "lado": "VENTA"
      },
      {
        "fecha_hora": "2026-07-07T15:58:35.276-03:00",
        "plazo": "CI",
        "moneda": "ARS",
        "precio": 156260.0,
        "nominales": 13632,
        "lado": "VENTA"
      },
      {
        "fecha_hora": "2026-07-07T16:16:10.737-03:00",
        "plazo": "CI",
        "moneda": "ARS",
        "precio": 156260.0,
        "nominales": 13632,
        "lado": "COMPRA"
      }
    ],
    "VSCRD": [
      {
        "fecha_hora": "2026-07-07T16:52:28.568-03:00",
        "plazo": "24hs",
        "moneda": "USD",
        "precio": 107.6,
        "nominales": 23336,
        "lado": "VENTA"
      },
      {
        "fecha_hora": "2026-07-07T14:59:54.201-03:00",
        "plazo": "24hs",
        "moneda": "USD",
        "precio": 108.65,
        "nominales": 10000,
        "lado": "VENTA"
      }
    ],
    "VSCRO": [
      {
        "fecha_hora": "2026-07-07T11:21:18.599-03:00",
        "plazo": "24hs",
        "moneda": "ARS",
        "precio": 165500.0,
        "nominales": 21035,
        "lado": "COMPRA"
      },
      {
        "fecha_hora": "2026-07-07T14:59:54.206-03:00",
        "plazo": "24hs",
        "moneda": "ARS",
        "precio": 166100.0,
        "nominales": 10000,
        "lado": "VENTA"
      }
    ],
    "VSCTD": [
      {
        "fecha_hora": "2026-07-07T10:59:01.863-03:00",
        "plazo": "24hs",
        "moneda": "USD",
        "precio": 107.45,
        "nominales": 10000,
        "lado": "COMPRA"
      },
      {
        "fecha_hora": "2026-07-07T11:15:43.032-03:00",
        "plazo": "24hs",
        "moneda": "USD",
        "precio": 107.45,
        "nominales": 10000,
        "lado": "DESCONOCIDO"
      },
      {
        "fecha_hora": "2026-07-07T12:03:49.202-03:00",
        "plazo": "24hs",
        "moneda": "USD",
        "precio": 107.3,
        "nominales": 10000,
        "lado": "COMPRA"
      },
      {
        "fecha_hora": "2026-07-07T12:16:26.978-03:00",
        "plazo": "24hs",
        "moneda": "USD",
        "precio": 107.3,
        "nominales": 10000,
        "lado": "DESCONOCIDO"
      }
    ],
    "VSCTO": [
      {
        "fecha_hora": "2026-07-07T12:04:59.537-03:00",
        "plazo": "24hs",
        "moneda": "ARS",
        "precio": 163800.0,
        "nominales": 10000,
        "lado": "COMPRA"
      },
      {
        "fecha_hora": "2026-07-07T12:05:41.81-03:00",
        "plazo": "24hs",
        "moneda": "ARS",
        "precio": 163800.0,
        "nominales": 10000,
        "lado": "COMPRA"
      },
      {
        "fecha_hora": "2026-07-07T16:20:35.824-03:00",
        "plazo": "24hs",
        "moneda": "ARS",
        "precio": 163800.0,
        "nominales": 10000,
        "lado": "COMPRA"
      },
      {
        "fecha_hora": "2026-07-07T16:31:56.854-03:00",
        "plazo": "24hs",
        "moneda": "ARS",
        "precio": 163800.0,
        "nominales": 10000,
        "lado": "DESCONOCIDO"
      }
    ],
    "VSCVD": [
      {
        "fecha_hora": "2026-07-07T11:06:14.221-03:00",
        "plazo": "24hs",
        "moneda": "USD",
        "precio": 110.7,
        "nominales": 30000,
        "lado": "COMPRA"
      },
      {
        "fecha_hora": "2026-07-07T12:36:17.269-03:00",
        "plazo": "24hs",
        "moneda": "USD",
        "precio": 110.6,
        "nominales": 14000,
        "lado": "VENTA"
      }
    ],
    "VSCVO": [
      {
        "fecha_hora": "2026-07-07T11:02:23.092-03:00",
        "plazo": "24hs",
        "moneda": "ARS",
        "precio": 169000.0,
        "nominales": 10000,
        "lado": "VENTA"
      }
    ],
    "VSCXD": [
      {
        "fecha_hora": "2026-07-07T10:57:38.943-03:00",
        "plazo": "24hs",
        "moneda": "USD",
        "precio": 108.55,
        "nominales": 15000,
        "lado": "VENTA"
      },
      {
        "fecha_hora": "2026-07-07T11:35:26.564-03:00",
        "plazo": "24hs",
        "moneda": "USD",
        "precio": 108.5,
        "nominales": 13000,
        "lado": "COMPRA"
      },
      {
        "fecha_hora": "2026-07-07T11:55:20.855-03:00",
        "plazo": "24hs",
        "moneda": "USD",
        "precio": 108.45,
        "nominales": 11000,
        "lado": "COMPRA"
      },
      {
        "fecha_hora": "2026-07-07T11:21:32.244-03:00",
        "plazo": "24hs",
        "moneda": "USD",
        "precio": 108.5,
        "nominales": 10000,
        "lado": "COMPRA"
      }
    ],
    "VSCXO": [
      {
        "fecha_hora": "2026-07-07T11:34:18.423-03:00",
        "plazo": "24hs",
        "moneda": "ARS",
        "precio": 165420.0,
        "nominales": 31000,
        "lado": "COMPRA"
      },
      {
        "fecha_hora": "2026-07-07T15:52:41.503-03:00",
        "plazo": "24hs",
        "moneda": "ARS",
        "precio": 165400.0,
        "nominales": 31000,
        "lado": "COMPRA"
      },
      {
        "fecha_hora": "2026-07-07T11:08:29.624-03:00",
        "plazo": "24hs",
        "moneda": "ARS",
        "precio": 165570.0,
        "nominales": 29000,
        "lado": "VENTA"
      },
      {
        "fecha_hora": "2026-07-07T11:08:30.901-03:00",
        "plazo": "24hs",
        "moneda": "ARS",
        "precio": 165570.0,
        "nominales": 28000,
        "lado": "COMPRA"
      },
      {
        "fecha_hora": "2026-07-07T11:34:31.07-03:00",
        "plazo": "24hs",
        "moneda": "ARS",
        "precio": 165420.0,
        "nominales": 25000,
        "lado": "COMPRA"
      },
      {
        "fecha_hora": "2026-07-07T11:34:45.76-03:00",
        "plazo": "24hs",
        "moneda": "ARS",
        "precio": 165420.0,
        "nominales": 21000,
        "lado": "COMPRA"
      },
      {
        "fecha_hora": "2026-07-07T11:21:47.969-03:00",
        "plazo": "24hs",
        "moneda": "ARS",
        "precio": 165500.0,
        "nominales": 19000,
        "lado": "COMPRA"
      },
      {
        "fecha_hora": "2026-07-07T11:42:42.327-03:00",
        "plazo": "24hs",
        "moneda": "ARS",
        "precio": 165420.0,
        "nominales": 19000,
        "lado": "COMPRA"
      },
      {
        "fecha_hora": "2026-07-07T11:08:46.247-03:00",
        "plazo": "24hs",
        "moneda": "ARS",
        "precio": 165570.0,
        "nominales": 18000,
        "lado": "COMPRA"
      },
      {
        "fecha_hora": "2026-07-07T11:19:35.091-03:00",
        "plazo": "24hs",
        "moneda": "ARS",
        "precio": 165500.0,
        "nominales": 17000,
        "lado": "VENTA"
      },
      {
        "fecha_hora": "2026-07-07T11:35:31.213-03:00",
        "plazo": "24hs",
        "moneda": "ARS",
        "precio": 165420.0,
        "nominales": 17000,
        "lado": "COMPRA"
      },
      {
        "fecha_hora": "2026-07-07T11:35:01.186-03:00",
        "plazo": "24hs",
        "moneda": "ARS",
        "precio": 165420.0,
        "nominales": 16000,
        "lado": "COMPRA"
      },
      {
        "fecha_hora": "2026-07-07T10:52:02.306-03:00",
        "plazo": "24hs",
        "moneda": "ARS",
        "precio": 165590.0,
        "nominales": 15000,
        "lado": "VENTA"
      },
      {
        "fecha_hora": "2026-07-07T10:57:38.926-03:00",
        "plazo": "24hs",
        "moneda": "ARS",
        "precio": 165600.0,
        "nominales": 15000,
        "lado": "VENTA"
      },
      {
        "fecha_hora": "2026-07-07T11:35:26.526-03:00",
        "plazo": "24hs",
        "moneda": "ARS",
        "precio": 165420.0,
        "nominales": 15000,
        "lado": "COMPRA"
      },
      {
        "fecha_hora": "2026-07-07T16:16:14.303-03:00",
        "plazo": "24hs",
        "moneda": "ARS",
        "precio": 165400.0,
        "nominales": 15000,
        "lado": "COMPRA"
      },
      {
        "fecha_hora": "2026-07-07T11:35:18.826-03:00",
        "plazo": "24hs",
        "moneda": "ARS",
        "precio": 165420.0,
        "nominales": 14000,
        "lado": "COMPRA"
      },
      {
        "fecha_hora": "2026-07-07T16:12:42.75-03:00",
        "plazo": "24hs",
        "moneda": "ARS",
        "precio": 165400.0,
        "nominales": 12000,
        "lado": "COMPRA"
      },
      {
        "fecha_hora": "2026-07-07T10:52:37.266-03:00",
        "plazo": "24hs",
        "moneda": "ARS",
        "precio": 165590.0,
        "nominales": 11000,
        "lado": "COMPRA"
      },
      {
        "fecha_hora": "2026-07-07T11:21:32.223-03:00",
        "plazo": "24hs",
        "moneda": "ARS",
        "precio": 165500.0,
        "nominales": 11000,
        "lado": "COMPRA"
      },
      {
        "fecha_hora": "2026-07-07T10:57:38.956-03:00",
        "plazo": "24hs",
        "moneda": "ARS",
        "precio": 165600.0,
        "nominales": 10000,
        "lado": "VENTA"
      }
    ],
    "XMC1D": [
      {
        "fecha_hora": "2026-07-07T11:58:55.465-03:00",
        "plazo": "24hs",
        "moneda": "USD",
        "precio": 103.3,
        "nominales": 20000,
        "lado": "VENTA"
      }
    ],
    "YCAMD": [
      {
        "fecha_hora": "2026-07-07T11:21:12.374-03:00",
        "plazo": "24hs",
        "moneda": "USD",
        "precio": 107.0,
        "nominales": 11000,
        "lado": "VENTA"
      },
      {
        "fecha_hora": "2026-07-07T11:22:08.138-03:00",
        "plazo": "24hs",
        "moneda": "USD",
        "precio": 107.0,
        "nominales": 11000,
        "lado": "DESCONOCIDO"
      },
      {
        "fecha_hora": "2026-07-07T11:08:49.88-03:00",
        "plazo": "24hs",
        "moneda": "USD",
        "precio": 110.0,
        "nominales": 10000,
        "lado": "COMPRA"
      },
      {
        "fecha_hora": "2026-07-07T11:08:50.671-03:00",
        "plazo": "24hs",
        "moneda": "USD",
        "precio": 110.0,
        "nominales": 10000,
        "lado": "COMPRA"
      }
    ],
    "YFCJD": [
      {
        "fecha_hora": "2026-07-07T12:36:00.989-03:00",
        "plazo": "24hs",
        "moneda": "USD",
        "precio": 107.6,
        "nominales": 15000,
        "lado": "VENTA"
      },
      {
        "fecha_hora": "2026-07-07T11:24:52.603-03:00",
        "plazo": "24hs",
        "moneda": "USD",
        "precio": 107.5,
        "nominales": 13000,
        "lado": "COMPRA"
      },
      {
        "fecha_hora": "2026-07-07T11:11:52.982-03:00",
        "plazo": "24hs",
        "moneda": "USD",
        "precio": 107.8,
        "nominales": 10000,
        "lado": "VENTA"
      },
      {
        "fecha_hora": "2026-07-07T11:32:15.046-03:00",
        "plazo": "24hs",
        "moneda": "USD",
        "precio": 107.5,
        "nominales": 10000,
        "lado": "COMPRA"
      }
    ],
    "YFCND": [
      {
        "fecha_hora": "2026-07-07T12:06:31.679-03:00",
        "plazo": "24hs",
        "moneda": "USD",
        "precio": 102.8,
        "nominales": 15000,
        "lado": "VENTA"
      }
    ],
    "YFCNO": [
      {
        "fecha_hora": "2026-07-07T12:06:28.855-03:00",
        "plazo": "CI",
        "moneda": "ARS",
        "precio": 156800.0,
        "nominales": 15000,
        "lado": "COMPRA"
      }
    ],
    "YM34D": [
      {
        "fecha_hora": "2026-07-07T14:10:52.929-03:00",
        "plazo": "24hs",
        "moneda": "USD",
        "precio": 111.7,
        "nominales": 30000,
        "lado": "VENTA"
      },
      {
        "fecha_hora": "2026-07-07T14:11:40.761-03:00",
        "plazo": "24hs",
        "moneda": "USD",
        "precio": 111.7,
        "nominales": 25985,
        "lado": "VENTA"
      },
      {
        "fecha_hora": "2026-07-07T14:14:52.44-03:00",
        "plazo": "24hs",
        "moneda": "USD",
        "precio": 111.7,
        "nominales": 22000,
        "lado": "VENTA"
      },
      {
        "fecha_hora": "2026-07-07T12:04:17.771-03:00",
        "plazo": "24hs",
        "moneda": "USD",
        "precio": 111.8,
        "nominales": 20085,
        "lado": "VENTA"
      },
      {
        "fecha_hora": "2026-07-07T14:17:40.197-03:00",
        "plazo": "24hs",
        "moneda": "USD",
        "precio": 111.7,
        "nominales": 20000,
        "lado": "VENTA"
      },
      {
        "fecha_hora": "2026-07-07T14:15:22.461-03:00",
        "plazo": "24hs",
        "moneda": "USD",
        "precio": 111.7,
        "nominales": 18000,
        "lado": "VENTA"
      },
      {
        "fecha_hora": "2026-07-07T14:17:03.034-03:00",
        "plazo": "24hs",
        "moneda": "USD",
        "precio": 111.7,
        "nominales": 15000,
        "lado": "VENTA"
      },
      {
        "fecha_hora": "2026-07-07T16:30:21.217-03:00",
        "plazo": "24hs",
        "moneda": "USD",
        "precio": 111.85,
        "nominales": 14735,
        "lado": "COMPRA"
      },
      {
        "fecha_hora": "2026-07-07T11:29:24.176-03:00",
        "plazo": "24hs",
        "moneda": "USD",
        "precio": 112.05,
        "nominales": 13745,
        "lado": "VENTA"
      },
      {
        "fecha_hora": "2026-07-07T14:06:44.988-03:00",
        "plazo": "24hs",
        "moneda": "USD",
        "precio": 111.85,
        "nominales": 13392,
        "lado": "VENTA"
      },
      {
        "fecha_hora": "2026-07-07T12:01:22.833-03:00",
        "plazo": "24hs",
        "moneda": "USD",
        "precio": 111.9,
        "nominales": 13351,
        "lado": "VENTA"
      },
      {
        "fecha_hora": "2026-07-07T11:07:41.036-03:00",
        "plazo": "24hs",
        "moneda": "USD",
        "precio": 112.2,
        "nominales": 12314,
        "lado": "COMPRA"
      },
      {
        "fecha_hora": "2026-07-07T14:06:49.561-03:00",
        "plazo": "24hs",
        "moneda": "USD",
        "precio": 111.85,
        "nominales": 11713,
        "lado": "VENTA"
      },
      {
        "fecha_hora": "2026-07-07T15:34:28.852-03:00",
        "plazo": "24hs",
        "moneda": "USD",
        "precio": 111.55,
        "nominales": 10603,
        "lado": "VENTA"
      },
      {
        "fecha_hora": "2026-07-07T12:04:17.766-03:00",
        "plazo": "24hs",
        "moneda": "USD",
        "precio": 111.85,
        "nominales": 10000,
        "lado": "VENTA"
      },
      {
        "fecha_hora": "2026-07-07T14:06:44.979-03:00",
        "plazo": "24hs",
        "moneda": "USD",
        "precio": 111.85,
        "nominales": 10000,
        "lado": "VENTA"
      },
      {
        "fecha_hora": "2026-07-07T14:06:44.985-03:00",
        "plazo": "24hs",
        "moneda": "USD",
        "precio": 111.8,
        "nominales": 10000,
        "lado": "VENTA"
      }
    ],
    "YM34O": [
      {
        "fecha_hora": "2026-07-07T15:36:36.301-03:00",
        "plazo": "24hs",
        "moneda": "ARS",
        "precio": 170000.0,
        "nominales": 38235,
        "lado": "COMPRA"
      },
      {
        "fecha_hora": "2026-07-07T15:19:53.713-03:00",
        "plazo": "24hs",
        "moneda": "ARS",
        "precio": 170500.0,
        "nominales": 33714,
        "lado": "COMPRA"
      },
      {
        "fecha_hora": "2026-07-07T16:35:47.768-03:00",
        "plazo": "24hs",
        "moneda": "ARS",
        "precio": 170750.0,
        "nominales": 26542,
        "lado": "VENTA"
      },
      {
        "fecha_hora": "2026-07-07T15:52:30.951-03:00",
        "plazo": "24hs",
        "moneda": "ARS",
        "precio": 170600.0,
        "nominales": 25000,
        "lado": "VENTA"
      },
      {
        "fecha_hora": "2026-07-07T12:23:00.637-03:00",
        "plazo": "24hs",
        "moneda": "ARS",
        "precio": 170920.0,
        "nominales": 20000,
        "lado": "VENTA"
      },
      {
        "fecha_hora": "2026-07-07T11:48:35.787-03:00",
        "plazo": "24hs",
        "moneda": "ARS",
        "precio": 171000.0,
        "nominales": 19008,
        "lado": "COMPRA"
      },
      {
        "fecha_hora": "2026-07-07T15:23:08.027-03:00",
        "plazo": "24hs",
        "moneda": "ARS",
        "precio": 170300.0,
        "nominales": 18529,
        "lado": "COMPRA"
      },
      {
        "fecha_hora": "2026-07-07T15:23:23.947-03:00",
        "plazo": "24hs",
        "moneda": "ARS",
        "precio": 170300.0,
        "nominales": 18009,
        "lado": "COMPRA"
      },
      {
        "fecha_hora": "2026-07-07T15:30:21.988-03:00",
        "plazo": "24hs",
        "moneda": "ARS",
        "precio": 170000.0,
        "nominales": 18009,
        "lado": "COMPRA"
      },
      {
        "fecha_hora": "2026-07-07T16:56:56.49-03:00",
        "plazo": "24hs",
        "moneda": "ARS",
        "precio": 170600.0,
        "nominales": 15212,
        "lado": "VENTA"
      },
      {
        "fecha_hora": "2026-07-07T15:17:41.912-03:00",
        "plazo": "24hs",
        "moneda": "ARS",
        "precio": 170580.0,
        "nominales": 15000,
        "lado": "VENTA"
      },
      {
        "fecha_hora": "2026-07-07T12:01:22.844-03:00",
        "plazo": "24hs",
        "moneda": "ARS",
        "precio": 171140.0,
        "nominales": 13351,
        "lado": "VENTA"
      },
      {
        "fecha_hora": "2026-07-07T14:06:44.996-03:00",
        "plazo": "24hs",
        "moneda": "ARS",
        "precio": 170950.0,
        "nominales": 12728,
        "lado": "VENTA"
      },
      {
        "fecha_hora": "2026-07-07T15:20:48.94-03:00",
        "plazo": "24hs",
        "moneda": "ARS",
        "precio": 170320.0,
        "nominales": 12000,
        "lado": "VENTA"
      },
      {
        "fecha_hora": "2026-07-07T15:22:52.932-03:00",
        "plazo": "24hs",
        "moneda": "ARS",
        "precio": 170320.0,
        "nominales": 12000,
        "lado": "VENTA"
      },
      {
        "fecha_hora": "2026-07-07T15:20:48.94-03:00",
        "plazo": "24hs",
        "moneda": "ARS",
        "precio": 170340.0,
        "nominales": 11741,
        "lado": "VENTA"
      },
      {
        "fecha_hora": "2026-07-07T14:06:49.582-03:00",
        "plazo": "24hs",
        "moneda": "ARS",
        "precio": 170950.0,
        "nominales": 11713,
        "lado": "VENTA"
      },
      {
        "fecha_hora": "2026-07-07T15:30:28.952-03:00",
        "plazo": "24hs",
        "moneda": "ARS",
        "precio": 170000.0,
        "nominales": 11393,
        "lado": "COMPRA"
      },
      {
        "fecha_hora": "2026-07-07T15:22:52.934-03:00",
        "plazo": "24hs",
        "moneda": "ARS",
        "precio": 170310.0,
        "nominales": 11207,
        "lado": "VENTA"
      },
      {
        "fecha_hora": "2026-07-07T16:53:16.969-03:00",
        "plazo": "24hs",
        "moneda": "ARS",
        "precio": 170600.0,
        "nominales": 11175,
        "lado": "VENTA"
      },
      {
        "fecha_hora": "2026-07-07T15:22:52.976-03:00",
        "plazo": "24hs",
        "moneda": "ARS",
        "precio": 170300.0,
        "nominales": 11032,
        "lado": "VENTA"
      },
      {
        "fecha_hora": "2026-07-07T15:34:28.74-03:00",
        "plazo": "24hs",
        "moneda": "ARS",
        "precio": 170000.0,
        "nominales": 10603,
        "lado": "VENTA"
      }
    ],
    "YM37D": [
      {
        "fecha_hora": "2026-07-07T11:43:02.647-03:00",
        "plazo": "24hs",
        "moneda": "USD",
        "precio": 104.1,
        "nominales": 14217,
        "lado": "COMPRA"
      },
      {
        "fecha_hora": "2026-07-07T11:43:02.65-03:00",
        "plazo": "24hs",
        "moneda": "USD",
        "precio": 104.55,
        "nominales": 12836,
        "lado": "COMPRA"
      }
    ],
    "YM38D": [
      {
        "fecha_hora": "2026-07-07T15:45:51.851-03:00",
        "plazo": "24hs",
        "moneda": "USD",
        "precio": 106.6,
        "nominales": 14829,
        "lado": "COMPRA"
      }
    ],
    "YM39D": [
      {
        "fecha_hora": "2026-07-07T11:34:58.876-03:00",
        "plazo": "24hs",
        "moneda": "USD",
        "precio": 114.0,
        "nominales": 13418,
        "lado": "VENTA"
      }
    ],
    "YM39O": [
      {
        "fecha_hora": "2026-07-07T11:34:58.855-03:00",
        "plazo": "24hs",
        "moneda": "ARS",
        "precio": 174450.0,
        "nominales": 13610,
        "lado": "VENTA"
      }
    ],
    "YM40D": [
      {
        "fecha_hora": "2026-07-07T12:30:41.083-03:00",
        "plazo": "24hs",
        "moneda": "USD",
        "precio": 106.05,
        "nominales": 87578,
        "lado": "VENTA"
      },
      {
        "fecha_hora": "2026-07-07T11:35:55.868-03:00",
        "plazo": "24hs",
        "moneda": "USD",
        "precio": 106.05,
        "nominales": 46557,
        "lado": "VENTA"
      }
    ],
    "YMCID": [
      {
        "fecha_hora": "2026-07-07T11:31:22.525-03:00",
        "plazo": "24hs",
        "moneda": "USD",
        "precio": 93.1,
        "nominales": 14090,
        "lado": "VENTA"
      }
    ],
    "YMCIO": [
      {
        "fecha_hora": "2026-07-07T12:14:51.685-03:00",
        "plazo": "24hs",
        "moneda": "ARS",
        "precio": 141200.0,
        "nominales": 29188,
        "lado": "COMPRA"
      },
      {
        "fecha_hora": "2026-07-07T12:20:22.531-03:00",
        "plazo": "24hs",
        "moneda": "ARS",
        "precio": 141200.0,
        "nominales": 21608,
        "lado": "COMPRA"
      },
      {
        "fecha_hora": "2026-07-07T11:31:22.381-03:00",
        "plazo": "24hs",
        "moneda": "ARS",
        "precio": 141940.0,
        "nominales": 14090,
        "lado": "VENTA"
      },
      {
        "fecha_hora": "2026-07-07T12:09:51.253-03:00",
        "plazo": "24hs",
        "moneda": "ARS",
        "precio": 141000.0,
        "nominales": 12000,
        "lado": "VENTA"
      }
    ],
    "YMCXD": [
      {
        "fecha_hora": "2026-07-07T11:21:03.589-03:00",
        "plazo": "24hs",
        "moneda": "USD",
        "precio": 113.3,
        "nominales": 27840,
        "lado": "COMPRA"
      },
      {
        "fecha_hora": "2026-07-07T10:44:11.988-03:00",
        "plazo": "24hs",
        "moneda": "USD",
        "precio": 113.6,
        "nominales": 10000,
        "lado": "VENTA"
      },
      {
        "fecha_hora": "2026-07-07T11:17:43.237-03:00",
        "plazo": "24hs",
        "moneda": "USD",
        "precio": 113.3,
        "nominales": 10000,
        "lado": "COMPRA"
      }
    ],
    "YMCXO": [
      {
        "fecha_hora": "2026-07-07T15:18:14.862-03:00",
        "plazo": "24hs",
        "moneda": "ARS",
        "precio": 172230.0,
        "nominales": 30000,
        "lado": "VENTA"
      },
      {
        "fecha_hora": "2026-07-07T15:23:36.063-03:00",
        "plazo": "24hs",
        "moneda": "ARS",
        "precio": 172050.0,
        "nominales": 30000,
        "lado": "VENTA"
      },
      {
        "fecha_hora": "2026-07-07T11:21:03.587-03:00",
        "plazo": "24hs",
        "moneda": "ARS",
        "precio": 173070.0,
        "nominales": 27840,
        "lado": "COMPRA"
      },
      {
        "fecha_hora": "2026-07-07T15:18:20.608-03:00",
        "plazo": "24hs",
        "moneda": "ARS",
        "precio": 172000.0,
        "nominales": 25300,
        "lado": "COMPRA"
      },
      {
        "fecha_hora": "2026-07-07T15:37:16.173-03:00",
        "plazo": "24hs",
        "moneda": "ARS",
        "precio": 172000.0,
        "nominales": 24216,
        "lado": "COMPRA"
      },
      {
        "fecha_hora": "2026-07-07T15:38:56.682-03:00",
        "plazo": "24hs",
        "moneda": "ARS",
        "precio": 172000.0,
        "nominales": 21825,
        "lado": "COMPRA"
      },
      {
        "fecha_hora": "2026-07-07T14:14:16.954-03:00",
        "plazo": "24hs",
        "moneda": "ARS",
        "precio": 172900.0,
        "nominales": 21760,
        "lado": "COMPRA"
      },
      {
        "fecha_hora": "2026-07-07T15:23:45.958-03:00",
        "plazo": "24hs",
        "moneda": "ARS",
        "precio": 172000.0,
        "nominales": 19795,
        "lado": "COMPRA"
      },
      {
        "fecha_hora": "2026-07-07T15:24:01.285-03:00",
        "plazo": "24hs",
        "moneda": "ARS",
        "precio": 172000.0,
        "nominales": 18137,
        "lado": "COMPRA"
      },
      {
        "fecha_hora": "2026-07-07T15:18:31.456-03:00",
        "plazo": "24hs",
        "moneda": "ARS",
        "precio": 172000.0,
        "nominales": 17050,
        "lado": "COMPRA"
      },
      {
        "fecha_hora": "2026-07-07T15:39:20.904-03:00",
        "plazo": "24hs",
        "moneda": "ARS",
        "precio": 172000.0,
        "nominales": 10000,
        "lado": "COMPRA"
      }
    ]
  }
}