[{"fecha":"19/06/2026","cierre":111.15,"monto":223468},{"fecha":"18/06/2026","cierre":111.45,"monto":290549},{"fecha":"17/06/2026","cierre":111.3,"monto":498906},{"fecha":"16/06/2026","cierre":111.95,"monto":835447},{"fecha":"12/06/2026","cierre":112.25,"monto":349693},{"fecha":"11/06/2026","cierre":111.95,"monto":544738},{"fecha":"10/06/2026","cierre":111.5,"monto":220501},{"fecha":"09/06/2026","cierre":111.0,"monto":503223},{"fecha":"08/06/2026","cierre":115.7,"monto":356142},{"fecha":"05/06/2026","cierre":116.35,"monto":468369},{"fecha":"04/06/2026","cierre":115.5,"monto":307788},{"fecha":"03/06/2026","cierre":115.5,"monto":182522},{"fecha":"02/06/2026","cierre":115.2,"monto":35629},{"fecha":"01/06/2026","cierre":115.0,"monto":299408},{"fecha":"29/05/2026","cierre":115.65,"monto":57387},{"fecha":"28/05/2026","cierre":114.75,"monto":579750},{"fecha":"27/05/2026","cierre":114.6,"monto":258318},{"fecha":"26/05/2026","cierre":114.95,"monto":480568},{"fecha":"22/05/2026","cierre":114.3,"monto":328137},{"fecha":"21/05/2026","cierre":114.65,"monto":637923},{"fecha":"20/05/2026","cierre":114.35,"monto":826720},{"fecha":"19/05/2026","cierre":113.7,"monto":843249},{"fecha":"18/05/2026","cierre":114.0,"monto":951828},{"fecha":"15/05/2026","cierre":114.5,"monto":381908},{"fecha":"14/05/2026","cierre":114.85,"monto":595387},{"fecha":"13/05/2026","cierre":114.7,"monto":301493},{"fecha":"12/05/2026","cierre":114.4,"monto":411857},{"fecha":"11/05/2026","cierre":114.5,"monto":284279},{"fecha":"08/05/2026","cierre":114.7,"monto":459752},{"fecha":"07/05/2026","cierre":114.4,"monto":385220},{"fecha":"06/05/2026","cierre":114.5,"monto":352299},{"fecha":"05/05/2026","cierre":114.0,"monto":489764},{"fecha":"04/05/2026","cierre":114.3,"monto":239692},{"fecha":"30/04/2026","cierre":114.25,"monto":395553},{"fecha":"29/04/2026","cierre":114.3,"monto":575232},{"fecha":"28/04/2026","cierre":113.9,"monto":331584},{"fecha":"27/04/2026","cierre":113.75,"monto":365742},{"fecha":"24/04/2026","cierre":114.0,"monto":374680},{"fecha":"23/04/2026","cierre":113.3,"monto":537491},{"fecha":"22/04/2026","cierre":113.45,"monto":735615},{"fecha":"21/04/2026","cierre":113.6,"monto":870845},{"fecha":"20/04/2026","cierre":113.5,"monto":313418},{"fecha":"17/04/2026","cierre":113.45,"monto":634757},{"fecha":"16/04/2026","cierre":113.0,"monto":1040696},{"fecha":"15/04/2026","cierre":112.7,"monto":766885},{"fecha":"14/04/2026","cierre":114.35,"monto":1779980},{"fecha":"13/04/2026","cierre":113.0,"monto":1009529},{"fecha":"10/04/2026","cierre":112.7,"monto":1906623},{"fecha":"09/04/2026","cierre":112.05,"monto":1019549},{"fecha":"08/04/2026","cierre":111.75,"monto":446139},{"fecha":"07/04/2026","cierre":111.65,"monto":762957},{"fecha":"06/04/2026","cierre":111.5,"monto":686273},{"fecha":"01/04/2026","cierre":111.4,"monto":775782},{"fecha":"31/03/2026","cierre":111.5,"monto":618727},{"fecha":"30/03/2026","cierre":111.35,"monto":613206},{"fecha":"27/03/2026","cierre":112.1,"monto":646295},{"fecha":"26/03/2026","cierre":111.65,"monto":576733},{"fecha":"25/03/2026","cierre":111.9,"monto":571862},{"fecha":"23/03/2026","cierre":112.15,"monto":59319},{"fecha":"20/03/2026","cierre":111.55,"monto":975022},{"fecha":"19/03/2026","cierre":111.45,"monto":785448},{"fecha":"18/03/2026","cierre":111.5,"monto":1147957},{"fecha":"17/03/2026","cierre":112.0,"monto":1350199},{"fecha":"16/03/2026","cierre":111.55,"monto":610530},{"fecha":"13/03/2026","cierre":111.15,"monto":990662},{"fecha":"12/03/2026","cierre":111.25,"monto":660498},{"fecha":"11/03/2026","cierre":111.45,"monto":866508},{"fecha":"10/03/2026","cierre":111.7,"monto":655466},{"fecha":"09/03/2026","cierre":111.05,"monto":284968},{"fecha":"06/03/2026","cierre":110.8,"monto":1090622},{"fecha":"05/03/2026","cierre":110.5,"monto":346747},{"fecha":"04/03/2026","cierre":110.4,"monto":486012},{"fecha":"03/03/2026","cierre":109.55,"monto":585821},{"fecha":"02/03/2026","cierre":109.7,"monto":478732},{"fecha":"27/02/2026","cierre":110.65,"monto":887107},{"fecha":"26/02/2026","cierre":110.35,"monto":500242},{"fecha":"25/02/2026","cierre":110.8,"monto":215661},{"fecha":"24/02/2026","cierre":111.4,"monto":309261},{"fecha":"23/02/2026","cierre":111.0,"monto":427486},{"fecha":"20/02/2026","cierre":111.0,"monto":632914},{"fecha":"19/02/2026","cierre":110.35,"monto":352263},{"fecha":"18/02/2026","cierre":110.1,"monto":686568},{"fecha":"13/02/2026","cierre":110.5,"monto":678211},{"fecha":"12/02/2026","cierre":109.65,"monto":6552},{"fecha":"11/02/2026","cierre":108.85,"monto":853475},{"fecha":"10/02/2026","cierre":108.85,"monto":703291},{"fecha":"09/02/2026","cierre":108.7,"monto":660478},{"fecha":"06/02/2026","cierre":108.7,"monto":625805},{"fecha":"05/02/2026","cierre":108.25,"monto":646774},{"fecha":"04/02/2026","cierre":108.35,"monto":738267},{"fecha":"03/02/2026","cierre":108.7,"monto":1409300},{"fecha":"02/02/2026","cierre":109.2,"monto":294886},{"fecha":"30/01/2026","cierre":108.75,"monto":1298266},{"fecha":"29/01/2026","cierre":109.0,"monto":989883},{"fecha":"28/01/2026","cierre":108.8,"monto":1284029},{"fecha":"27/01/2026","cierre":108.3,"monto":1316878},{"fecha":"26/01/2026","cierre":107.75,"monto":1565776},{"fecha":"23/01/2026","cierre":107.55,"monto":1203009},{"fecha":"22/01/2026","cierre":108.0,"monto":1164075},{"fecha":"21/01/2026","cierre":107.5,"monto":1221090},{"fecha":"20/01/2026","cierre":107.3,"monto":698452},{"fecha":"19/01/2026","cierre":107.4,"monto":744848},{"fecha":"16/01/2026","cierre":107.0,"monto":709882},{"fecha":"15/01/2026","cierre":107.1,"monto":853109},{"fecha":"14/01/2026","cierre":106.9,"monto":908731},{"fecha":"13/01/2026","cierre":107.15,"monto":733022},{"fecha":"12/01/2026","cierre":107.0,"monto":732262},{"fecha":"09/01/2026","cierre":106.9,"monto":612361},{"fecha":"08/01/2026","cierre":106.65,"monto":433290},{"fecha":"07/01/2026","cierre":106.8,"monto":561153},{"fecha":"06/01/2026","cierre":107.15,"monto":569733},{"fecha":"05/01/2026","cierre":106.5,"monto":635539},{"fecha":"02/01/2026","cierre":106.2,"monto":737114},{"fecha":"30/12/2025","cierre":106.0,"monto":713218},{"fecha":"29/12/2025","cierre":106.6,"monto":565168},{"fecha":"26/12/2025","cierre":107.0,"monto":14995},{"fecha":"24/12/2025","cierre":106.5,"monto":26694},{"fecha":"23/12/2025","cierre":106.75,"monto":1636310},{"fecha":"22/12/2025","cierre":107.25,"monto":703949},{"fecha":"19/12/2025","cierre":106.0,"monto":755490},{"fecha":"18/12/2025","cierre":106.4,"monto":758762},{"fecha":"17/12/2025","cierre":106.0,"monto":521593},{"fecha":"16/12/2025","cierre":105.5,"monto":894549},{"fecha":"15/12/2025","cierre":105.25,"monto":612318},{"fecha":"12/12/2025","cierre":104.7,"monto":9425},{"fecha":"11/12/2025","cierre":104.5,"monto":497893},{"fecha":"10/12/2025","cierre":104.6,"monto":581781},{"fecha":"09/12/2025","cierre":104.9,"monto":848404},{"fecha":"05/12/2025","cierre":110.4,"monto":991646},{"fecha":"04/12/2025","cierre":109.55,"monto":735679},{"fecha":"03/12/2025","cierre":109.0,"monto":598874},{"fecha":"02/12/2025","cierre":109.85,"monto":498811},{"fecha":"01/12/2025","cierre":109.15,"monto":182924},{"fecha":"28/11/2025","cierre":109.95,"monto":375962},{"fecha":"27/11/2025","cierre":109.85,"monto":197711},{"fecha":"26/11/2025","cierre":109.65,"monto":663580},{"fecha":"25/11/2025","cierre":110.8,"monto":171586},{"fecha":"21/11/2025","cierre":111.0,"monto":57751},{"fecha":"20/11/2025","cierre":110.7,"monto":580674},{"fecha":"19/11/2025","cierre":110.0,"monto":361576},{"fecha":"18/11/2025","cierre":110.0,"monto":477556},{"fecha":"17/11/2025","cierre":110.1,"monto":389617},{"fecha":"14/11/2025","cierre":109.95,"monto":998637},{"fecha":"13/11/2025","cierre":109.25,"monto":676877},{"fecha":"12/11/2025","cierre":109.4,"monto":585617},{"fecha":"11/11/2025","cierre":109.3,"monto":318681},{"fecha":"10/11/2025","cierre":109.3,"monto":20634},{"fecha":"07/11/2025","cierre":109.1,"monto":612828},{"fecha":"06/11/2025","cierre":109.85,"monto":34028},{"fecha":"05/11/2025","cierre":109.05,"monto":810443},{"fecha":"04/11/2025","cierre":108.95,"monto":491587},{"fecha":"03/11/2025","cierre":109.7,"monto":726560},{"fecha":"31/10/2025","cierre":109.3,"monto":953453},{"fecha":"30/10/2025","cierre":109.25,"monto":526180},{"fecha":"29/10/2025","cierre":108.1,"monto":950799},{"fecha":"28/10/2025","cierre":108.0,"monto":723938},{"fecha":"27/10/2025","cierre":107.4,"monto":503370},{"fecha":"24/10/2025","cierre":105.45,"monto":589056},{"fecha":"23/10/2025","cierre":104.55,"monto":783801},{"fecha":"22/10/2025","cierre":105.0,"monto":340069},{"fecha":"21/10/2025","cierre":104.85,"monto":461633},{"fecha":"20/10/2025","cierre":104.4,"monto":456106},{"fecha":"17/10/2025","cierre":104.4,"monto":606245},{"fecha":"16/10/2025","cierre":104.75,"monto":578439},{"fecha":"15/10/2025","cierre":104.05,"monto":608938},{"fecha":"14/10/2025","cierre":105.0,"monto":433987},{"fecha":"13/10/2025","cierre":105.4,"monto":617925},{"fecha":"09/10/2025","cierre":106.0,"monto":582394},{"fecha":"08/10/2025","cierre":106.0,"monto":328081},{"fecha":"07/10/2025","cierre":105.5,"monto":523842},{"fecha":"06/10/2025","cierre":105.7,"monto":540625},{"fecha":"03/10/2025","cierre":106.25,"monto":379066},{"fecha":"02/10/2025","cierre":107.15,"monto":502091},{"fecha":"01/10/2025","cierre":107.5,"monto":435458},{"fecha":"30/09/2025","cierre":107.7,"monto":563956},{"fecha":"29/09/2025","cierre":107.8,"monto":413153},{"fecha":"26/09/2025","cierre":107.75,"monto":801911},{"fecha":"25/09/2025","cierre":107.15,"monto":623897},{"fecha":"24/09/2025","cierre":106.9,"monto":535645},{"fecha":"23/09/2025","cierre":106.65,"monto":987765},{"fecha":"22/09/2025","cierre":105.45,"monto":997545},{"fecha":"19/09/2025","cierre":104.3,"monto":1037205},{"fecha":"18/09/2025","cierre":105.0,"monto":1739088},{"fecha":"11/09/2025","cierre":104.7,"monto":49213},{"fecha":"10/09/2025","cierre":104.3,"monto":474912},{"fecha":"09/09/2025","cierre":103.5,"monto":1153810},{"fecha":"08/09/2025","cierre":103.0,"monto":406987},{"fecha":"05/09/2025","cierre":104.65,"monto":879001},{"fecha":"04/09/2025","cierre":103.85,"monto":1583084},{"fecha":"03/09/2025","cierre":104.0,"monto":617008},{"fecha":"02/09/2025","cierre":103.35,"monto":722936},{"fecha":"01/09/2025","cierre":104.7,"monto":337205},{"fecha":"29/08/2025","cierre":104.5,"monto":436300},{"fecha":"28/08/2025","cierre":104.5,"monto":661703},{"fecha":"27/08/2025","cierre":104.5,"monto":645300},{"fecha":"26/08/2025","cierre":104.5,"monto":764764},{"fecha":"25/08/2025","cierre":105.1,"monto":658141},{"fecha":"22/08/2025","cierre":106.25,"monto":356615},{"fecha":"21/08/2025","cierre":106.2,"monto":222307},{"fecha":"20/08/2025","cierre":105.8,"monto":468051},{"fecha":"19/08/2025","cierre":106.7,"monto":1200269},{"fecha":"18/08/2025","cierre":106.6,"monto":166504},{"fecha":"14/08/2025","cierre":106.45,"monto":769574},{"fecha":"13/08/2025","cierre":106.5,"monto":585436},{"fecha":"12/08/2025","cierre":105.5,"monto":984362},{"fecha":"11/08/2025","cierre":104.95,"monto":492348},{"fecha":"08/08/2025","cierre":105.1,"monto":437607},{"fecha":"07/08/2025","cierre":104.85,"monto":477586},{"fecha":"06/08/2025","cierre":104.65,"monto":599644},{"fecha":"05/08/2025","cierre":104.5,"monto":1063431},{"fecha":"04/08/2025","cierre":104.65,"monto":588223},{"fecha":"01/08/2025","cierre":104.5,"monto":484578},{"fecha":"31/07/2025","cierre":104.5,"monto":483637},{"fecha":"30/07/2025","cierre":104.45,"monto":475453},{"fecha":"29/07/2025","cierre":104.5,"monto":606041},{"fecha":"28/07/2025","cierre":104.7,"monto":455227},{"fecha":"25/07/2025","cierre":104.7,"monto":617620},{"fecha":"24/07/2025","cierre":104.4,"monto":496357},{"fecha":"23/07/2025","cierre":104.8,"monto":333693},{"fecha":"22/07/2025","cierre":104.4,"monto":454674},{"fecha":"21/07/2025","cierre":104.25,"monto":378002},{"fecha":"18/07/2025","cierre":104.75,"monto":612808},{"fecha":"17/07/2025","cierre":104.5,"monto":531564},{"fecha":"16/07/2025","cierre":104.2,"monto":1325802},{"fecha":"15/07/2025","cierre":104.2,"monto":1051811},{"fecha":"14/07/2025","cierre":104.7,"monto":916452},{"fecha":"11/07/2025","cierre":103.95,"monto":1225352},{"fecha":"10/07/2025","cierre":103.6,"monto":1044407},{"fecha":"08/07/2025","cierre":102.95,"monto":1136898},{"fecha":"07/07/2025","cierre":102.95,"monto":798789},{"fecha":"04/07/2025","cierre":103.5,"monto":723522},{"fecha":"03/07/2025","cierre":103.2,"monto":703487},{"fecha":"02/07/2025","cierre":102.9,"monto":998706},{"fecha":"30/06/2025","cierre":102.45,"monto":1934235},{"fecha":"27/06/2025","cierre":102.5,"monto":1916714},{"fecha":"26/06/2025","cierre":102.4,"monto":1329513},{"fecha":"25/06/2025","cierre":102.2,"monto":681776},{"fecha":"24/06/2025","cierre":102.25,"monto":1106668},{"fecha":"23/06/2025","cierre":101.8,"monto":1131295},{"fecha":"19/06/2025","cierre":101.75,"monto":654124},{"fecha":"18/06/2025","cierre":101.85,"monto":1335635},{"fecha":"17/06/2025","cierre":101.55,"monto":933824},{"fecha":"13/06/2025","cierre":102.5,"monto":1090547},{"fecha":"12/06/2025","cierre":101.4,"monto":2221797}]